Workbook

Sheet All_India_Index_Upto_April23_RA
A1: Sector | B1: Year | C1: Month | D1: Cereals and products | E1: Meat and fish | F1: Egg | G1: Milk and products | H1: Oils and fats | I1: Fruits | J1: Vegetables | K1: Pulses and products | L1: Sugar and Confectionery | M1: Spices | N1: Non-alcoholic beverages | O1: Prepared meals, snacks, sweets etc. | P1: Food and beverages | Q1: Pan, tobacco and intoxicants | R1: Clothing | S1: Footwear | T1: Clothing and footwear | U1: Housing | V1: Fuel and light | W1: Household goods and services | X1: Health | Y1: Transport and communication | Z1: Recreation and amusement | AA1: Education | AB1: Personal care and effects | AC1: Miscellaneous | AD1: General index
A2: Rural | B2: 2013 | C2: January | D2: 107.5 | E2: 106.3 | F2: 108.1 | G2: 104.9 | H2: 106.1 | I2: 103.9 | J2: 101.9 | K2: 106.1 | L2: 106.8 | M2: 103.1 | N2: 104.8 | O2: 106.7 | P2: 105.5 | Q2: 105.1 | R2: 106.5 | S2: 105.8 | T2: 106.4 | U2: NA | V2: 105.5 | W2: 104.8 | X2: 104 | Y2: 103.3 | Z2: 103.4 | AA2: 103.8 | AB2: 104.7 | AC2: 104 | AD2: 105.1
A3: Urban | B3: 2013 | C3: January | D3: 110.5 | E3: 109.1 | F3: 113 | G3: 103.6 | H3: 103.4 | I3: 102.3 | J3: 102.9 | K3: 105.8 | L3: 105.1 | M3: 101.8 | N3: 105.1 | O3: 107.9 | P3: 105.9 | Q3: 105.2 | R3: 105.9 | S3: 105 | T3: 105.8 | U3: 100.3 | V3: 105.4 | W3: 104.8 | X3: 104.1 | Y3: 103.2 | Z3: 102.9 | AA3: 103.5 | AB3: 104.3 | AC3: 103.7 | AD3: 104
A4: Rural+Urban | B4: 2013 | C4: January | D4: 108.4 | E4: 107.3 | F4: 110 | G4: 104.4 | H4: 105.1 | I4: 103.2 | J4: 102.2 | K4: 106 | L4: 106.2 | M4: 102.7 | N4: 104.9 | O4: 107.3 | P4: 105.6 | Q4: 105.1 | R4: 106.3 | S4: 105.5 | T4: 106.2 | U4: 100.3 | V4: 105.5 | W4: 104.8 | X4: 104 | Y4: 103.2 | Z4: 103.1 | AA4: 103.6 | AB4: 104.5 | AC4: 103.9 | AD4: 104.6
A5: Rural | B5: 2013 | C5: February | D5: 109.2 | E5: 108.7 | F5: 110.2 | G5: 105.4 | H5: 106.7 | I5: 104 | J5: 102.4 | K5: 105.9 | L5: 105.7 | M5: 103.1 | N5: 105.1 | O5: 107.7 | P5: 106.3 | Q5: 105.6 | R5: 107.1 | S5: 106.3 | T5: 107 | U5: NA | V5: 106.2 | W5: 105.2 | X5: 104.4 | Y5: 103.9 | Z5: 104 | AA5: 104.1 | AB5: 104.6 | AC5: 104.4 | AD5: 105.8
A6: Urban | B6: 2013 | C6: February | D6: 112.9 | E6: 112.9 | F6: 116.9 | G6: 104 | H6: 103.5 | I6: 103.1 | J6: 104.9 | K6: 104.1 | L6: 103.8 | M6: 102.3 | N6: 106 | O6: 109 | P6: 107.2 | Q6: 106 | R6: 106.6 | S6: 105.5 | T6: 106.4 | U6: 100.4 | V6: 105.7 | W6: 105.2 | X6: 104.7 | Y6: 104.4 | Z6: 103.3 | AA6: 103.7 | AB6: 104.3 | AC6: 104.3 | AD6: 104.7
A7: Rural+Urban | B7: 2013 | C7: February | D7: 110.4 | E7: 110.2 | F7: 112.8 | G7: 104.9 | H7: 105.5 | I7: 103.6 | J7: 103.2 | K7: 105.3 | L7: 105.1 | M7: 102.8 | N7: 105.5 | O7: 108.3 | P7: 106.6 | Q7: 105.7 | R7: 106.9 | S7: 106 | T7: 106.8 | U7: 100.4 | V7: 106 | W7: 105.2 | X7: 104.5 | Y7: 104.2 | Z7: 103.6 | AA7: 103.9 | AB7: 104.5 | AC7: 104.4 | AD7: 105.3
A8: Rural | B8: 2013 | C8: March | D8: 110.2 | E8: 108.8 | F8: 109.9 | G8: 105.6 | H8: 106.2 | I8: 105.7 | J8: 101.4 | K8: 105.7 | L8: 105 | M8: 103.3 | N8: 105.6 | O8: 108.2 | P8: 106.6 | Q8: 106.5 | R8: 107.6 | S8: 106.8 | T8: 107.5 | U8: NA | V8: 106.1 | W8: 105.6 | X8: 104.7 | Y8: 104.6 | Z8: 104 | AA8: 104.3 | AB8: 104.3 | AC8: 104.6 | AD8: 106
A9: Urban | B9: 2013 | C9: March | D9: 113.9 | E9: 111.4 | F9: 113.2 | G9: 104.3 | H9: 102.7 | I9: 104.9 | J9: 103.8 | K9: 103.5 | L9: 102.6 | M9: 102.4 | N9: 107 | O9: 109.8 | P9: 107.3 | Q9: 106.8 | R9: 107.2 | S9: 106 | T9: 107 | U9: 100.4 | V9: 106 | W9: 105.7 | X9: 105.2 | Y9: 105.5 | Z9: 103.5 | AA9: 103.8 | AB9: 104.2 | AC9: 104.9 | AD9: 105
A10: Rural+Urban | B10: 2013 | C10: March | D10: 111.4 | E10: 109.7 | F10: 111.2 | G10: 105.1 | H10: 104.9 | I10: 105.3 | J10: 102.2 | K10: 105 | L10: 104.2 | M10: 103 | N10: 106.2 | O10: 108.9 | P10: 106.9 | Q10: 106.6 | R10: 107.4 | S10: 106.5 | T10: 107.3 | U10: 100.4 | V10: 106.1 | W10: 105.6 | X10: 104.9 | Y10: 105.1 | Z10: 103.7 | AA10: 104 | AB10: 104.3 | AC10: 104.7 | AD10: 105.5
A11: Rural | B11: 2013 | C11: April | D11: 110.2 | E11: 109.5 | F11: 106.9 | G11: 106.3 | H11: 105.7 | I11: 108.3 | J11: 103.4 | K11: 105.7 | L11: 104.2 | M11: 103.2 | N11: 106.5 | O11: 108.8 | P11: 107.1 | Q11: 107.1 | R11: 108.1 | S11: 107.4 | T11: 108 | U11: NA | V11: 106.5 | W11: 106.1 | X11: 105.1 | Y11: 104.4 | Z11: 104.5 | AA11: 104.8 | AB11: 102.7 | AC11: 104.6 | AD11: 106.4
A12: Urban | B12: 2013 | C12: April | D12: 114.6 | E12: 113.4 | F12: 106 | G12: 104.7 | H12: 102.1 | I12: 109.5 | J12: 109.7 | K12: 104.6 | L12: 102 | M12: 103.5 | N12: 108.2 | O12: 110.6 | P12: 108.8 | Q12: 108.5 | R12: 107.9 | S12: 106.4 | T12: 107.7 | U12: 100.5 | V12: 106.4 | W12: 106.5 | X12: 105.7 | Y12: 105 | Z12: 104 | AA12: 105.2 | AB12: 103.2 | AC12: 105.1 | AD12: 105.7
A13: Rural+Urban | B13: 2013 | C13: April | D13: 111.6 | E13: 110.9 | F13: 106.6 | G13: 105.7 | H13: 104.4 | I13: 108.9 | J13: 105.5 | K13: 105.3 | L13: 103.5 | M13: 103.3 | N13: 107.2 | O13: 109.6 | P13: 107.7 | Q13: 107.5 | R13: 108 | S13: 107 | T13: 107.9 | U13: 100.5 | V13: 106.5 | W13: 106.3 | X13: 105.3 | Y13: 104.7 | Z13: 104.2 | AA13: 105 | AB13: 102.9 | AC13: 104.8 | AD13: 106.1
... A259: Rural+Urban | B259: 2020 | C259: March | D259: 145.1 | E259: 167 | F259: 148.1 | G259: 151.5 | H259: 131.2 | I259: 142.5 | J259: 157.3 | K259: 141.1 | L259: 113.2 | M259: 153.2 | N259: 136.7 | O259: 159.6 | P259: 148.9 | Q259: 171.2 | R259: 151.2 | S259: 141.9 | T259: 149.8 | U259: 154.5 | V259: 148.9 | W259: 146.4 | X259: 152.3 | Y259: 129.9 | Z259: 143.7 | AA259: 156.1 | AB259: 145.2 | AC259: 143.8 | AD259: 148.6
A260: Rural | B260: 2020 | C260: April | D260: 147.2 | F260: 146.9 | G260: 155.6 | H260: 137.1 | I260: 147.3 | J260: 162.7 | K260: 150.2 | L260: 119.8 | M260: 158.7 | N260: 139.2 | P260: 150.1 | U260: NA | V260: 148.4 | X260: 154.3
A261: Urban | B261: 2020 | C261: April | D261: 151.8 | F261: 151.9 | G261: 155.5 | H261: 131.6 | I261: 152.9 | J261: 180 | K261: 150.8 | L261: 121.2 | M261: 154 | N261: 133.5 | P261: 153.5 | U261: 155.6 | V261: 137.1 | X261: 144.8
A262: Rural+Urban | B262: 2020 | C262: April | D262: 148.7 | F262: 148.8 | G262: 155.6 | H262: 135.1 | I262: 149.9 | J262: 168.6 | K262: 150.4 | L262: 120.3 | M262: 157.1 | N262: 136.8 | P262: 151.4 | U262: 155.6 | V262: 144.1 | X262: 150.7
A263: Rural | B263: 2020 | C263: May | U263: NA
A264: Urban | B264: 2020 | C264: May | U264: NA
A265: Rural+Urban | B265: 2020 | C265: May | U265: NA
A266: Rural | B266: 2020 | C266: June | D266: 148.2 | E266: 190.3 | F266: 149.4 | G266: 153.3 | H266: 138.2 | I266: 143.2 | J266: 148.9 | K266: 150.3 | L266: 113.2 | M266: 159.8 | N266: 142.1 | O266: 161.8 | P266: 152.3 | Q266: 182.4 | R266: 154.7 | S266: 150 | T266: 154.1 | U266: NA | V266: 144.9 | W266: 151.7 | X266: 158.2 | Y266: 141.4 | Z266: 153.2 | AA266: 161.8 | AB266: 151.2 | AC266: 151.7 | AD266: 152.7
A267: Urban | B267: 2020 | C267: June | D267: 152.7 | E267: 197 | F267: 154.6 | G267: 153.4 | H267: 132.9 | I267: 151.8 | J267: 171.2 | K267: 152 | L267: 116.3 | M267: 158.8 | N267: 135.6 | O267: 161.7 | P267: 157 | Q267: 186.7 | R267: 149.1 | S267: 136.6 | T267: 147.2 | U267: 154.7 | V267: 137.1 | W267: 140.4 | X267: 148.1 | Y267: 129.3 | Z267: 144.5 | AA267: 152.5 | AB267: 152.2 | AC267: 142 | AD267: 150.8
A268: Rural+Urban | B268: 2020 | C268: June | D268: 149.6 | E268: 192.7 | F268: 151.4 | G268: 153.3 | H268: 136.3 | I268: 147.2 | J268: 156.5 | K268: 150.9 | L268: 114.2 | M268: 159.5 | N268: 139.4 | O268: 161.8 | P268: 154 | Q268: 183.5 | R268: 152.5 | S268: 144.4 | T268: 151.4 | U268: 154.7 | V268: 141.9 | W268: 146.4 | X268: 154.4 | Y268: 135 | Z268: 148.3 | AA268: 156.4 | AB268: 151.6 | AC268: 147 | AD268: 151.8
A269: Rural | B269: 2020 | C269: July | D269: 148.2 | E269: 190.3 | F269: 149.4 | G269: 153.3 | H269: 138.2 | I269: 143.2 | J269: 148.9 | K269: 150.3 | L269: 113.2 | M269: 159.8 | N269: 142.1 | O269: 161.8 | P269: 152.3 | Q269: 182.4 | R269: 154.7 | S269: 150 | T269: 154.1 | U269: NA | V269: 144.9 | W269: 151.7 | X269: 158.2 | Y269: 141.4 | Z269: 153.2 | AA269: 161.8 | AB269: 151.2 | AC269: 151.7 | AD269: 152.7
A270: Urban | B270: 2020 | C270: July | D270: 152.7 | E270: 197 | F270: 154.6 | G270: 153.4 | H270: 132.9 | I270: 151.8 | J270: 171.2 | K270: 152 | L270: 116.3 | M270: 158.8 | N270: 135.6 | O270: 161.7 | P270: 157 | Q270: 186.7 | R270: 149.1 | S270: 136.6 | T270: 147.2 | U270: 154.7 | V270: 137.1 | W270: 140.4 | X270: 148.1 | Y270: 129.3 | Z270: 144.5 | AA270: 152.5 | AB270: 152.2 | AC270: 142 | AD270: 150.8
A271: Rural+Urban | B271: 2020 | C271: July | D271: 149.6 | E271: 192.7 | F271: 151.4 | G271: 153.3 | H271: 136.3 | I271: 147.2 | J271: 156.5 | K271: 150.9 | L271: 114.2 | M271: 159.5 | N271: 139.4 | O271: 161.8 | P271: 154 | Q271: 183.5 | R271: 152.5 | S271: 144.4 | T271: 151.4 | U271: 154.7 | V271: 141.9 | W271: 146.4 | X271: 154.4 | Y271: 135 | Z271: 148.3 | AA271: 156.4 | AB271: 151.6 | AC271: 147 | AD271: 151.8
A272: Rural | B272: 2020 | C272: August | D272: 147.6 | E272: 187.2 | F272: 148.4 | G272: 153.3 | H272: 139.8 | I272: 146.9 | J272: 171 | K272: 149.9 | L272: 114.2 | M272: 160 | N272: 143.5 | O272: 161.5 | P272: 155.3 | Q272: 180.9 | R272: 155.1 | S272: 149.3 | T272: 154.3 | U272: NA | V272: 145.8 | W272: 151.9 | X272: 158.8 | Y272: 143.6 | Z272: 152.2 | AA272: 162.7 | AB272: 153.6 | AC272: 153 | AD272: 154.7
A273: Urban | B273: 2020 | C273: August | D273: 151.6 | E273: 197.8 | F273: 154.5 | G273: 153.4 | H273: 133.4 | I273: 154.5 | J273: 191.9 | K273: 151.3 | L273: 116.8 | M273: 160 | N273: 136.5 | O273: 163.3 | P273: 159.9 | Q273: 187.2 | R273: 150 | S273: 135.2 | T273: 147.8 | U273: 155.5 | V273: 138.3 | W273: 144.5 | X273: 148.7 | Y273: 133.9 | Z273: 141.2 | AA273: 155.5 | AB273: 155.2 | AC273: 144.8 | AD273: 152.9
A274: Rural+Urban | B274: 2020 | C274: August | D274: 148.9 | E274: 190.9 | F274: 150.8 | G274: 153.3 | H274: 137.4 | I274: 150.4 | J274: 178.1 | K274: 150.4 | L274: 115.1 | M274: 160 | N274: 140.6 | O274: 162.3 | P274: 157 | Q274: 182.6 | R274: 153.1 | S274: 143.4 | T274: 151.7 | U274: 155.5 | V274: 143 | W274: 148.4 | X274: 155 | Y274: 138.5 | Z274: 146 | AA274: 158.5 | AB274: 154.3 | AC274: 149 | AD274: 153.9
A275: Rural | B275: 2020 | C275: September | D275: 146.9 | E275: 183.9 | F275: 149.5 | G275: 153.4 | H275: 140.4 | I275: 147 | J275: 178.8 | K275: 149.3 | L275: 115.1 | M275: 160 | N275: 145.4 | O275: 161.6 | P275: 156.1 | Q275: 182.9 | R275: 155.4 | S275: 149.9 | T275: 154.6 | U275: NA | V275: 146.4 | W275: 151.6 | X275: 159.1 | Y275: 144.6 | Z275: 152.8 | AA275: 161.1 | AB275: 157.4 | AC275: 153.7 | AD275: 155.4
A276: Urban | B276: 2020 | C276: September | D276: 151.5 | E276: 193.1 | F276: 157.3 | G276: 153.9 | H276: 134.4 | I276: 155.4 | J276: 202 | K276: 150.8 | L276: 118.9 | M276: 160.9 | N276: 137.7 | O276: 164.4 | P276: 161.3 | Q276: 188.7 | R276: 150.2 | S276: 136.3 | T276: 148.1 | U276: 156.3 | V276: 137.2 | W276: 145.4 | X276: 150 | Y276: 135.1 | Z276: 141.8 | AA276: 154.9 | AB276: 159.8 | AC276: 146 | AD276: 154
A277: Rural+Urban | B277: 2020 | C277: September | D277: 148.4 | E277: 187.1 | F277: 152.5 | G277: 153.6 | H277: 138.2 | I277: 150.9 | J277: 186.7 | K277: 149.8 | L277: 116.4 | M277: 160.3 | N277: 142.2 | O277: 162.9 | P277: 158 | Q277: 184.4 | R277: 153.4 | S277: 144.3 | T277: 152 | U277: 156.3 | V277: 142.9 | W277: 148.7 | X277: 155.6 | Y277: 139.6 | Z277: 146.6 | AA277: 157.5 | AB277: 158.4 | AC277: 150 | AD277: 154.7
... A373: Rural+Urban | B373: 2023 | C373: May | D373: 173.7 | E373: 214.3 | F373: 173.2 | G373: 179.5 | H373: 170 | I373: 172.2 | J373: 161 | K373: 175.6 | L373: 122.7 | M373: 218 | N373: 173.4 | O373: 194.2 | P373: 179.1 | Q373: 201 | R373: 187.3 | S373: 179.7 | T373: 186.2 | U373: 175.6 | V373: 182.8 | W373: 175.2 | X373: 185.7 | Y373: 164.8 | Z373: 171.2 | AA373: 177.1 | AB373: 185.2 | AC373: 175.7 | AD373: 179.1

Sheet Raw Data
A1: Sector | B1: Year | C1: Month | D1: Cereals and products | E1: Meat and fish | F1: Egg | G1: Milk and products | H1: Oils and fats | I1: Fruits | J1: Vegetables | K1: Pulses and products | L1: Sugar and Confectionery | M1: Spices | N1: Non-alcoholic beverages | O1: Prepared meals, snacks, sweets etc. | P1: Food and beverages | Q1: Pan, tobacco and intoxicants | R1: Clothing | S1: Footwear | T1: Clothing and footwear | U1: Housing | V1: Fuel and light | W1: Household goods and services | X1: Health | Y1: Transport and communication | Z1: Recreation and amusement | AA1: Education | AB1: Personal care and effects | AC1: Miscellaneous | AD1: General index
A2: Rural | B2: 2013 | C2: January | D2: 107.5 | E2: 106.3 | F2: 108.1 | G2: 104.9 | H2: 106.1 | I2: 103.9 | J2: 101.9 | K2: 106.1 | L2: 106.8 | M2: 103.1 | N2: 104.8 | O2: 106.7 | P2: 105.5 | Q2: 105.1 | R2: 106.5 | S2: 105.8 | T2: 106.4 | U2: NA | V2: 105.5 | W2: 104.8 | X2: 104 | Y2: 103.3 | Z2: 103.4 | AA2: 103.8 | AB2: 104.7 | AC2: 104 | AD2: 105.1
A3: Urban | B3: 2013 | C3: January | D3: 110.5 | E3: 109.1 | F3: 113 | G3: 103.6 | H3: 103.4 | I3: 102.3 | J3: 102.9 | K3: 105.8 | L3: 105.1 | M3: 101.8 | N3: 105.1 | O3: 107.9 | P3: 105.9 | Q3: 105.2 | R3: 105.9 | S3: 105 | T3: 105.8 | U3: 100.3 | V3: 105.4 | W3: 104.8 | X3: 104.1 | Y3: 103.2 | Z3: 102.9 | AA3: 103.5 | AB3: 104.3 | AC3: 103.7 | AD3: 104
A4: Rural+Urban | B4: 2013 | C4: January | D4: 108.4 | E4: 107.3 | F4: 110 | G4: 104.4 | H4: 105.1 | I4: 103.2 | J4: 102.2 | K4: 106 | L4: 106.2 | M4: 102.7 | N4: 104.9 | O4: 107.3 | P4: 105.6 | Q4: 105.1 | R4: 106.3 | S4: 105.5 | T4: 106.2 | U4: 100.3 | V4: 105.5 | W4: 104.8 | X4: 104 | Y4: 103.2 | Z4: 103.1 | AA4: 103.6 | AB4: 104.5 | AC4: 103.9 | AD4: 104.6
A5: Rural | B5: 2013 | C5: February | D5: 109.2 | E5: 108.7 | F5: 110.2 | G5: 105.4 | H5: 106.7 | I5: 104 | J5: 102.4 | K5: 105.9 | L5: 105.7 | M5: 103.1 | N5: 105.1 | O5: 107.7 | P5: 106.3 | Q5: 105.6 | R5: 107.1 | S5: 106.3 | T5: 107 | U5: NA | V5: 106.2 | W5: 105.2 | X5: 104.4 | Y5: 103.9 | Z5: 104 | AA5: 104.1 | AB5: 104.6 | AC5: 104.4 | AD5: 105.8
A6: Urban | B6: 2013 | C6: February | D6: 112.9 | E6: 112.9 | F6: 116.9 | G6: 104 | H6: 103.5 | I6: 103.1 | J6: 104.9 | K6: 104.1 | L6: 103.8 | M6: 102.3 | N6: 106 | O6: 109 | P6: 107.2 | Q6: 106 | R6: 106.6 | S6: 105.5 | T6: 106.4 | U6: 100.4 | V6: 105.7 | W6: 105.2 | X6: 104.7 | Y6: 104.4 | Z6: 103.3 | AA6: 103.7 | AB6: 104.3 | AC6: 104.3 | AD6: 104.7
A7: Rural+Urban | B7: 2013 | C7: February | D7: 110.4 | E7: 110.2 | F7: 112.8 | G7: 104.9 | H7: 105.5 | I7: 103.6 | J7: 103.2 | K7: 105.3 | L7: 105.1 | M7: 102.8 | N7: 105.5 | O7: 108.3 | P7: 106.6 | Q7: 105.7 | R7: 106.9 | S7: 106 | T7: 106.8 | U7: 100.4 | V7: 106 | W7: 105.2 | X7: 104.5 | Y7: 104.2 | Z7: 103.6 | AA7: 103.9 | AB7: 104.5 | AC7: 104.4 | AD7: 105.3
A8: Rural | B8: 2013 | C8: March | D8: 110.2 | E8: 108.8 | F8: 109.9 | G8: 105.6 | H8: 106.2 | I8: 105.7 | J8: 101.4 | K8: 105.7 | L8: 105 | M8: 103.3 | N8: 105.6 | O8: 108.2 | P8: 106.6 | Q8: 106.5 | R8: 107.6 | S8: 106.8 | T8: 107.5 | U8: NA | V8: 106.1 | W8: 105.6 | X8: 104.7 | Y8: 104.6 | Z8: 104 | AA8: 104.3 | AB8: 104.3 | AC8: 104.6 | AD8: 106
A9: Urban | B9: 2013 | C9: March | D9: 113.9 | E9: 111.4 | F9: 113.2 | G9: 104.3 | H9: 102.7 | I9: 104.9 | J9: 103.8 | K9: 103.5 | L9: 102.6 | M9: 102.4 | N9: 107 | O9: 109.8 | P9: 107.3 | Q9: 106.8 | R9: 107.2 | S9: 106 | T9: 107 | U9: 100.4 | V9: 106 | W9: 105.7 | X9: 105.2 | Y9: 105.5 | Z9: 103.5 | AA9: 103.8 | AB9: 104.2 | AC9: 104.9 | AD9: 105
A10: Rural+Urban | B10: 2013 | C10: March | D10: 111.4 | E10: 109.7 | F10: 111.2 | G10: 105.1 | H10: 104.9 | I10: 105.3 | J10: 102.2 | K10: 105 | L10: 104.2 | M10: 103 | N10: 106.2 | O10: 108.9 | P10: 106.9 | Q10: 106.6 | R10: 107.4 | S10: 106.5 | T10: 107.3 | U10: 100.4 | V10: 106.1 | W10: 105.6 | X10: 104.9 | Y10: 105.1 | Z10: 103.7 | AA10: 104 | AB10: 104.3 | AC10: 104.7 | AD10: 105.5
A11: Rural | B11: 2013 | C11: April | D11: 110.2 | E11: 109.5 | F11: 106.9 | G11: 106.3 | H11: 105.7 | I11: 108.3 | J11: 103.4 | K11: 105.7 | L11: 104.2 | M11: 103.2 | N11: 106.5 | O11: 108.8 | P11: 107.1 | Q11: 107.1 | R11: 108.1 | S11: 107.4 | T11: 108 | U11: NA | V11: 106.5 | W11: 106.1 | X11: 105.1 | Y11: 104.4 | Z11: 104.5 | AA11: 104.8 | AB11: 102.7 | AC11: 104.6 | AD11: 106.4
A12: Urban | B12: 2013 | C12: April | D12: 114.6 | E12: 113.4 | F12: 106 | G12: 104.7 | H12: 102.1 | I12: 109.5 | J12: 109.7 | K12: 104.6 | L12: 102 | M12: 103.5 | N12: 108.2 | O12: 110.6 | P12: 108.8 | Q12: 108.5 | R12: 107.9 | S12: 106.4 | T12: 107.7 | U12: 100.5 | V12: 106.4 | W12: 106.5 | X12: 105.7 | Y12: 105 | Z12: 104 | AA12: 105.2 | AB12: 103.2 | AC12: 105.1 | AD12: 105.7
A13: Rural+Urban | B13: 2013 | C13: April | D13: 111.6 | E13: 110.9 | F13: 106.6 | G13: 105.7 | H13: 104.4 | I13: 108.9 | J13: 105.5 | K13: 105.3 | L13: 103.5 | M13: 103.3 | N13: 107.2 | O13: 109.6 | P13: 107.7 | Q13: 107.5 | R13: 108 | S13: 107 | T13: 107.9 | U13: 100.5 | V13: 106.5 | W13: 106.3 | X13: 105.3 | Y13: 104.7 | Z13: 104.2 | AA13: 105 | AB13: 102.9 | AC13: 104.8 | AD13: 106.1
... A259: Rural+Urban | B259: 2020 | C259: March | D259: 145.1 | E259: 167 | F259: 148.1 | G259: 151.5 | H259: 131.2 | I259: 142.5 | J259: 157.3 | K259: 141.1 | L259: 113.2 | M259: 153.2 | N259: 136.7 | O259: 159.6 | P259: 148.9 | Q259: 171.2 | R259: 151.2 | S259: 141.9 | T259: 149.8 | U259: 154.5 | V259: 148.9 | W259: 146.4 | X259: 152.3 | Y259: 129.9 | Z259: 143.7 | AA259: 156.1 | AB259: 145.2 | AC259: 143.8 | AD259: 148.6
A260: Rural | B260: 2020 | C260: April | D260: 147.2 | E260: =SUM(E257,E266)/2 -> 178.55 | F260: 146.9 | G260: 155.6 | H260: 137.1 | I260: 147.3 | J260: 162.7 | K260: 150.2 | L260: 119.8 | M260: 158.7 | N260: 139.2 | O260: =SUM(O257,O266)/2 -> 160.9 | P260: 150.1 | Q260: =SUM(Q257,Q266)/2 -> 176.45 | R260: =SUM(R257,R266)/2 -> 154.05 | S260: =SUM(S257,S266)/2 -> 148.8 | T260: =SUM(T257,T266)/2 -> 153.3 | U260: NA | V260: 148.4 | W260: =SUM(W257,W266)/2 -> 151.6 | X260: 154.3 | Y260: =SUM(Y257,Y266)/2 -> 138.6 | Z260: =SUM(Z257,Z266)/2 -> 152.2 | AA260: =SUM(AA257,AA266)/2 -> 161.5 | AB260: =SUM(AB257,AB266)/2 -> 148.15 | AC260: =SUM(AC257,AC266)/2 -> 150.15 | AD260: =SUM(AD257,AD266)/2 -> 151.25
A261: Urban | B261: 2020 | C261: April | D261: 151.8 | E261: =SUM(E258,E267)/2 -> 182.25 | F261: 151.9 | G261: 155.5 | H261: 131.6 | I261: 152.9 | J261: 180 | K261: 150.8 | L261: 121.2 | M261: 154 | N261: 133.5 | O261: =SUM(O258,O267)/2 -> 160.4 | P261: 153.5 | Q261: =SUM(Q258,Q267)/2 -> 180 | R261: =SUM(R258,R267)/2 -> 148.4 | S261: =SUM(S258,S267)/2 -> 135.2 | T261: =SUM(T258,T267)/2 -> 146.4 | U261: 155.6 | V261: 137.1 | W261: =SUM(W258,W267)/2 -> 140.6 | X261: 144.8 | Y261: =SUM(Y258,Y267)/2 -> 126.95 | Z261: =SUM(Z258,Z267)/2 -> 141.2 | AA261: =SUM(AA258,AA267)/2 -> 152.5 | AB261: =SUM(AB258,AB267)/2 -> 148.75 | AC261: =SUM(AC258,AC267)/2 -> 140.35 | AD261: =SUM(AD258,AD267)/2 -> 149.05
A262: Rural+Urban | B262: 2020 | C262: April | D262: 148.7 | E262: =SUM(E259,E268)/2 -> 179.85 | F262: 148.8 | G262: 155.6 | H262: 135.1 | I262: 149.9 | J262: 168.6 | K262: 150.4 | L262: 120.3 | M262: 157.1 | N262: 136.8 | O262: =SUM(O259,O268)/2 -> 160.7 | P262: 151.4 | Q262: =SUM(Q259,Q268)/2 -> 177.35 | R262: =SUM(R259,R268)/2 -> 151.85 | S262: =SUM(S259,S268)/2 -> 143.15 | T262: =SUM(T259,T268)/2 -> 150.6 | U262: 155.6 | V262: 144.1 | W262: =SUM(W259,W268)/2 -> 146.4 | X262: 150.7 | Y262: =SUM(Y259,Y268)/2 -> 132.45 | Z262: =SUM(Z259,Z268)/2 -> 146 | AA262: =SUM(AA259,AA268)/2 -> 156.25 | AB262: =SUM(AB259,AB268)/2 -> 148.4 | AC262: =SUM(AC259,AC268)/2 -> 145.4 | AD262: =SUM(AD259,AD268)/2 -> 150.2
A263: Rural | B263: 2020 | C263: May | D263: =SUM(D260,D266)/2 -> 147.7 | E263: =SUM(E260,E266)/2 -> 184.425 | F263: =SUM(F260,F266)/2 -> 148.15 | G263: =SUM(G260,G266)/2 -> 154.45 | H263: =SUM(H260,H266)/2 -> 137.65 | I263: =SUM(I260,I266)/2 -> 145.25 | J263: =SUM(J260,J266)/2 -> 155.8 | K263: =SUM(K260,K266)/2 -> 150.25 | ... T263: =SUM(T260,T266)/2 -> 153.7 | U263: NA | V263: =SUM(V260,V266)/2 -> 146.65 | W263: =SUM(W260,W266)/2 -> 151.65 | X263: =SUM(X260,X266)/2 -> 156.25 | Y263: =SUM(Y260,Y266)/2 -> 140 | Z263: =SUM(Z260,Z266)/2 -> 152.7 | AA263: =SUM(AA260,AA266)/2 -> 161.65 | AB263: =SUM(AB260,AB266)/2 -> 149.675 | AC263: =SUM(AC260,AC266)/2 -> 150.925 | AD263: =SUM(AD260,AD266)/2 -> 151.975
A264: Urban | B264: 2020 | C264: May | D264: =SUM(D261,D267)/2 -> 152.25 | E264: =SUM(E261,E267)/2 -> 189.625 | F264: =SUM(F261,F267)/2 -> 153.25 | G264: =SUM(G261,G267)/2 -> 154.45 | H264: =SUM(H261,H267)/2 -> 132.25 | I264: =SUM(I261,I267)/2 -> 152.35 | J264: =SUM(J261,J267)/2 -> 175.6 | K264: =SUM(K263,K265)/2 -> 150.45 | L264: =SUM(L261,L267)/2 -> 118.75 | M264: =SUM(M261,M267)/2 -> 156.4 | N264: =SUM(N261,N267)/2 -> 134.55 | O264: =SUM(O261,O267)/2 -> 161.05 | P264: =SUM(P261,P267)/2 -> 155.25 | Q264: =SUM(Q261,Q267)/2 -> 183.35 | R264: =SUM(R261,R267)/2 -> 148.75 | S264: =SUM(S261,S267)/2 -> 135.9 | T264: =SUM(T261,T267)/2 -> 146.8 | U264: NA | V264: =SUM(V261,V267)/2 -> 137.1 | W264: =SUM(,W261,W267)/2 -> 140.5 | X264: =SUM(X261,X267)/2 -> 146.45 | Y264: =SUM(Y261,Y267)/2 -> 128.125 | Z264: =SUM(Z261,Z267)/2 -> 142.85 | AA264: =SUM(AA261,AA267)/2 -> 152.5 | AB264: =SUM(AB261,AB267)/2 -> 150.475 | AC264: =SUM(AC261,AC267)/2 -> 141.175 | AD264: =SUM(AD261,AD267)/2 -> 149.925
A265: Rural+Urban | B265: 2020 | C265: May | D265: =SUM(D262,D268)/2 -> 149.15 | E265: =SUM(E262,E268)/2 -> 186.275 | F265: =SUM(F262,F268)/2 -> 150.1 | G265: =SUM(G262,G268)/2 -> 154.45 | H265: =SUM(H262,H268)/2 -> 135.7 | I265: =SUM(I262,I268)/2 -> 148.55 | J265: =SUM(J262,J268)/2 -> 162.55 | K265: =SUM(K262,K268)/2 -> 150.65 | ... T265: =SUM(T262,T268)/2 -> 151 | U265: NA | V265: =SUM(V262,V268)/2 -> 143 | W265: =SUM(W262,W268)/2 -> 146.4 | X265: =SUM(X262,X268)/2 -> 152.55 | Y265: =SUM(Y262,Y268)/2 -> 133.725 | Z265: =SUM(Z262,Z268)/2 -> 147.15 | AA265: =SUM(AA262,AA268)/2 -> 156.325 | AB265: =SUM(AB262,AB268)/2 -> 150 | AC265: =SUM(AC262,AC268)/2 -> 146.2 | AD265: =SUM(AD262,AD268)/2 -> 151
A266: Rural | B266: 2020 | C266: June | D266: 148.2 | E266: 190.3 | F266: 149.4 | G266: 153.3 | H266: 138.2 | I266: 143.2 | J266: 148.9 | K266: 150.3 | L266: 113.2 | M266: 159.8 | N266: 142.1 | O266: 161.8 | P266: 152.3 | Q266: 182.4 | R266: 154.7 | S266: 150 | T266: 154.1 | U266: NA | V266: 144.9 | W266: 151.7 | X266: 158.2 | Y266: 141.4 | Z266: 153.2 | AA266: 161.8 | AB266: 151.2 | AC266: 151.7 | AD266: 152.7
A267: Urban | B267: 2020 | C267: June | D267: 152.7 | E267: 197 | F267: 154.6 | G267: 153.4 | H267: 132.9 | I267: 151.8 | J267: 171.2 | K267: 152 | L267: 116.3 | M267: 158.8 | N267: 135.6 | O267: 161.7 | P267: 157 | Q267: 186.7 | R267: 149.1 | S267: 136.6 | T267: 147.2 | U267: 154.7 | V267: 137.1 | W267: 140.4 | X267: 148.1 | Y267: 129.3 | Z267: 144.5 | AA267: 152.5 | AB267: 152.2 | AC267: 142 | AD267: 150.8
A268: Rural+Urban | B268: 2020 | C268: June | D268: 149.6 | E268: 192.7 | F268: 151.4 | G268: 153.3 | H268: 136.3 | I268: 147.2 | J268: 156.5 | K268: 150.9 | L268: 114.2 | M268: 159.5 | N268: 139.4 | O268: 161.8 | P268: 154 | Q268: 183.5 | R268: 152.5 | S268: 144.4 | T268: 151.4 | U268: 154.7 | V268: 141.9 | W268: 146.4 | X268: 154.4 | Y268: 135 | Z268: 148.3 | AA268: 156.4 | AB268: 151.6 | AC268: 147 | AD268: 151.8
A269: Rural | B269: 2020 | C269: July | D269: 148.2 | E269: 190.3 | F269: 149.4 | G269: 153.3 | H269: 138.2 | I269: 143.2 | J269: 148.9 | K269: 150.3 | L269: 113.2 | M269: 159.8 | N269: 142.1 | O269: 161.8 | P269: 152.3 | Q269: 182.4 | R269: 154.7 | S269: 150 | T269: 154.1 | U269: NA | V269: 144.9 | W269: 151.7 | X269: 158.2 | Y269: 141.4 | Z269: 153.2 | AA269: 161.8 | AB269: 151.2 | AC269: 151.7 | AD269: 152.7
A270: Urban | B270: 2020 | C270: July | D270: 152.7 | E270: 197 | F270: 154.6 | G270: 153.4 | H270: 132.9 | I270: 151.8 | J270: 171.2 | K270: 152 | L270: 116.3 | M270: 158.8 | N270: 135.6 | O270: 161.7 | P270: 157 | Q270: 186.7 | R270: 149.1 | S270: 136.6 | T270: 147.2 | U270: 154.7 | V270: 137.1 | W270: 140.4 | X270: 148.1 | Y270: 129.3 | Z270: 144.5 | AA270: 152.5 | AB270: 152.2 | AC270: 142 | AD270: 150.8
A271: Rural+Urban | B271: 2020 | C271: July | D271: 149.6 | E271: 192.7 | F271: 151.4 | G271: 153.3 | H271: 136.3 | I271: 147.2 | J271: 156.5 | K271: 150.9 | L271: 114.2 | M271: 159.5 | N271: 139.4 | O271: 161.8 | P271: 154 | Q271: 183.5 | R271: 152.5 | S271: 144.4 | T271: 151.4 | U271: 154.7 | V271: 141.9 | W271: 146.4 | X271: 154.4 | Y271: 135 | Z271: 148.3 | AA271: 156.4 | AB271: 151.6 | AC271: 147 | AD271: 151.8
A272: Rural | B272: 2020 | C272: August | D272: 147.6 | E272: 187.2 | F272: 148.4 | G272: 153.3 | H272: 139.8 | I272: 146.9 | J272: 171 | K272: 149.9 | L272: 114.2 | M272: 160 | N272: 143.5 | O272: 161.5 | P272: 155.3 | Q272: 180.9 | R272: 155.1 | S272: 149.3 | T272: 154.3 | U272: NA | V272: 145.8 | W272: 151.9 | X272: 158.8 | Y272: 143.6 | Z272: 152.2 | AA272: 162.7 | AB272: 153.6 | AC272: 153 | AD272: 154.7
A273: Urban | B273: 2020 | C273: August | D273: 151.6 | E273: 197.8 | F273: 154.5 | G273: 153.4 | H273: 133.4 | I273: 154.5 | J273: 191.9 | K273: 151.3 | L273: 116.8 | M273: 160 | N273: 136.5 | O273: 163.3 | P273: 159.9 | Q273: 187.2 | R273: 150 | S273: 135.2 | T273: 147.8 | U273: 155.5 | V273: 138.3 | W273: 144.5 | X273: 148.7 | Y273: 133.9 | Z273: 141.2 | AA273: 155.5 | AB273: 155.2 | AC273: 144.8 | AD273: 152.9
A274: Rural+Urban | B274: 2020 | C274: August | D274: 148.9 | E274: 190.9 | F274: 150.8 | G274: 153.3 | H274: 137.4 | I274: 150.4 | J274: 178.1 | K274: 150.4 | L274: 115.1 | M274: 160 | N274: 140.6 | O274: 162.3 | P274: 157 | Q274: 182.6 | R274: 153.1 | S274: 143.4 | T274: 151.7 | U274: 155.5 | V274: 143 | W274: 148.4 | X274: 155 | Y274: 138.5 | Z274: 146 | AA274: 158.5 | AB274: 154.3 | AC274: 149 | AD274: 153.9
A275: Rural | B275: 2020 | C275: September | D275: 146.9 | E275: 183.9 | F275: 149.5 | G275: 153.4 | H275: 140.4 | I275: 147 | J275: 178.8 | K275: 149.3 | L275: 115.1 | M275: 160 | N275: 145.4 | O275: 161.6 | P275: 156.1 | Q275: 182.9 | R275: 155.4 | S275: 149.9 | T275: 154.6 | U275: NA | V275: 146.4 | W275: 151.6 | X275: 159.1 | Y275: 144.6 | Z275: 152.8 | AA275: 161.1 | AB275: 157.4 | AC275: 153.7 | AD275: 155.4
A276: Urban | B276: 2020 | C276: September | D276: 151.5 | E276: 193.1 | F276: 157.3 | G276: 153.9 | H276: 134.4 | I276: 155.4 | J276: 202 | K276: 150.8 | L276: 118.9 | M276: 160.9 | N276: 137.7 | O276: 164.4 | P276: 161.3 | Q276: 188.7 | R276: 150.2 | S276: 136.3 | T276: 148.1 | U276: 156.3 | V276: 137.2 | W276: 145.4 | X276: 150 | Y276: 135.1 | Z276: 141.8 | AA276: 154.9 | AB276: 159.8 | AC276: 146 | AD276: 154
A277: Rural+Urban | B277: 2020 | C277: September | D277: 148.4 | E277: 187.1 | F277: 152.5 | G277: 153.6 | H277: 138.2 | I277: 150.9 | J277: 186.7 | K277: 149.8 | L277: 116.4 | M277: 160.3 | N277: 142.2 | O277: 162.9 | P277: 158 | Q277: 184.4 | R277: 153.4 | S277: 144.3 | T277: 152 | U277: 156.3 | V277: 142.9 | W277: 148.7 | X277: 155.6 | Y277: 139.6 | Z277: 146.6 | AA277: 157.5 | AB277: 158.4 | AC277: 150 | AD277: 154.7
... A373: Rural+Urban | B373: 2023 | C373: May | D373: 173.7 | E373: 214.3 | F373: 173.2 | G373: 179.5 | H373: 170 | I373: 172.2 | J373: 161 | K373: 175.6 | L373: 122.7 | M373: 218 | N373: 173.4 | O373: 194.2 | P373: 179.1 | Q373: 201 | R373: 187.3 | S373: 179.7 | T373: 186.2 | U373: 175.6 | V373: 182.8 | W373: 175.2 | X373: 185.7 | Y373: 164.8 | Z373: 171.2 | AA373: 177.1 | AB373: 185.2 | AC373: 175.7 | AD373: 179.1

Sheet Notes
A1: Password for main data sheet - Bhagya
A3: Notes: The corrections that were made in the data, for solving the problem statement.
A4: Column Name | B4: Remarks | C4: Corrections done
A5: Sector | B5: Represents various categories of goods and services for Rural, Urban, Rural+Urban. | C5: No corrections was done in this column.
A6: Year | B6: The year the CPI data was recorded | C6: No corrections was made in this column.
A7: Month | B7: The month corresponding to the CPI data. | C7: No corrections was done in this column.
A8: Cereals and products | B8: Price index for cereals and related products. | C8: Missing values was handled by moving averages for May 2020
A9: Meat and fish | B9: Price index for meat and fish products. | C9: Missing values was handled by moving averages for April, May 2020.
A10: Egg | B10: Price index for eggs. | C10: Missing values was handled by moving averages for May 2020
A11: Milk and products | B11: Price index for milk and dairy products. | C11: Missing values was handled by moving averages.
A12: Oils and fats | B12: Price index for oils and fats. | C12: Missing values was handled by moving averages.
A13: Fruits | B13: Price index for fruits. | C13: Missing values was handled by moving averages.
A14: Vegetables | B14: Price index for vegetables. | C14: Missing values was handled by moving averages.
A15: Pulses and products | B15: Price index for pulses (lentils, bean) and products. | C15: Missing values was handled by moving averages.
... A34: General index | B34: The overall inflation index that combines all categories | C34: Missing values was handled by moving averages for April, May 2020.

Sheet PS1
A1: 45047
A2: The following is done for problem statement 1.
A3: 1.Based on the latest month’s data, identify the contribution of different broader categories (food, energy, transportation, education, etc.) towards the CPI basket. Broader categories (buckets) can be created by combining similar categories into one bucket; Ex.: Meals, Beverages, Cereals, can be clubbed to create “Food” category, etc.
A4: Which broader category has the highest contribution towards CPI calculation
A5: Contribution is calculated by evaluating the underlying index values for broader category and should add to 100% when contribution from different broader categories are added .
A6: Sector | B6: Category | C6: Rural | D6: Urban | E6: Rural+Urban | I6: Rural | J6: Rural% | K6: Urban | L6: Urban% | M6: Rural+Urban | N6: Rural+Urban%
A7: Cereals and products | B7: Food | C7: 173.2 | D7: 174.7 | E7: 173.7 | H7: Food | I7: =SUMIF($B$7:$B$32,H7,$C$7:$C$32) -> 2290.7 | J7: =I7/$I$13 -> 0.50918023 | K7: =SUMIF($B$7:$B$32,H7,$D$7:$D$32) -> 2335.1 | L7: =K7/$K$13 -> 0.52294359 | M7: =SUMIF($B$7:$B$32,H7,$E$7:$E$32) -> 2306.9 | N7: =M7/$M$13 -> 0.515071
A8: Meat and fish | B8: Food | C8: 211.5 | D8: 219.4 | E8: 214.3 | H8: Misc | I8: =SUMIF($B$7:$B$32,H8,$C$7:$C$32) -> 1088.1 | J8: =I8/$I$13 -> 0.2418645 | K8: =SUMIF($B$7:$B$32,H8,$D$7:$D$32) -> 1065.8 | L8: =K8/$K$13 -> 0.23868497 | M8: =SUMIF($B$7:$B$32,H8,$E$7:$E$32) -> 1075 | N8: =M8/$M$13 -> 0.24001965
A9: Egg | B9: Food | C9: 171 | D9: 176.7 | E9: 173.2 | H9: Clothing | I9: =SUMIF($B$7:$B$32,H9,$C$7:$C$32) -> 569.9 | J9: =I9/$I$13 -> 0.12667823 | K9: =SUMIF($B$7:$B$32,H9,$D$7:$D$32) -> 528.7 | L9: =K9/$K$13 -> 0.1184019 | M9: =SUMIF($B$7:$B$32,H9,$E$7:$E$32) -> 553.2 | N9: =M9/$M$13 -> 0.12351523
A10: Milk and products | B10: Food | C10: 179.6 | D10: 179.4 | E10: 179.5 | H10: Housing | I10: =SUMIF($B$7:$B$32,H10,$C$7:$C$32) -> 179.8 | J10: =I10/$I$13 -> 0.039966213 | K10: =SUMIF($B$7:$B$32,H10,$D$7:$D$32) -> 170.1 | L10: =K10/$K$13 -> 0.038093745 | M10: =SUMIF($B$7:$B$32,H10,$E$7:$E$32) -> 175.2 | N10: =M10/$M$13 -> 0.039117621
A11: Oils and fats | B11: Food | C11: 173.3 | D11: 164.4 | E11: 170 | H11: Energy | I11: =SUMIF($B$7:$B$32,H11,$C$7:$C$32) -> 182.5 | J11: =I11/$I$13 -> 0.040566373 | K11: =SUMIF($B$7:$B$32,H11,$D$7:$D$32) -> 183.4 | L11: =K11/$K$13 -> 0.041072268 | M11: =SUMIF($B$7:$B$32,H11,$E$7:$E$32) -> 182.8 | N11: =M11/$M$13 -> 0.040814504
A12: Fruits | B12: Food | C12: 169 | D12: 175.8 | E12: 172.2 | H12: Health | I12: =SUMIF($B$7:$B$32,H12,$C$7:$C$32) -> 187.8 | J12: =I12/$I$13 -> 0.041744465 | K12: =SUMIF($B$7:$B$32,H12,$D$7:$D$32) -> 182.2 | L12: =K12/$K$13 -> 0.040803529 | M12: =SUMIF($B$7:$B$32,H12,$E$7:$E$32) -> 185.7 | N12: =M12/$M$13 -> 0.041461999
A13: Vegetables | B13: Food | C13: 148.7 | D13: 185 | E13: 161 | I13: =SUM(I7:I12) -> 4498.8 | K13: =SUM(K7:K12) -> 4465.3 | M13: =SUM(M7:M12) -> 4478.8
A14: Pulses and products | B14: Food | C14: 174.9 | D14: 176.9 | E14: 175.6
A15: Sugar and Confectionery | B15: Food | C15: 121.9 | D15: 124.2 | E15: 122.7
A16: Spices | B16: Food | C16: 221 | D16: 211.9 | E16: 218
A17: Non-alcoholic beverages | B17: Food | C17: 178.7 | D17: 165.9 | E17: 173.4
A18: Prepared meals, snacks, sweets etc. | B18: Food | C18: 191.1 | D18: 197.7 | E18: 194.2
A19: Food and beverages | B19: Food | C19: 176.8 | D19: 183.1 | E19: 179.1
A20: Pan, tobacco and intoxicants | B20: Misc | C20: 199.9 | D20: 204.2 | E20: 201
A21: Clothing | B21: Clothing | C21: 191.2 | D21: 181.3 | E21: 187.3
A22: Footwear | B22: Clothing | C22: 187.9 | D22: 168.1 | E22: 179.7
A23: Clothing and footwear | B23: Clothing | C23: 190.8 | D23: 179.3 | E23: 186.2
A24: Housing | B24: Housing | C24: - | D24: 175.6 | E24: 175.6
A25: Fuel and light | B25: Energy | C25: 182.5 | D25: 183.4 | E25: 182.8
A26: Household goods and services | B26: Housing | C26: 179.8 | D26: 170.1 | E26: 175.2
A27: Health | B27: Health | C27: 187.8 | D27: 182.2 | E27: 185.7
A28: Transport and communication | B28: Misc | C28: 169.7 | D28: 160.4 | E28: 164.8
A29: Recreation and amusement | B29: Misc | C29: 173.8 | D29: 169.2 | E29: 171.2
A30: Education | B30: Misc | C30: 180.3 | D30: 174.8 | E30: 177.1
A31: Personal care and effects | B31: Misc | C31: 184.9 | D31: 185.6 | E31: 185.2
A32: Miscellaneous | B32: Misc | C32: 179.5 | D32: 171.6 | E32: 175.7

Sheet PS2
A1: 2. A trend of Y-o-Y increase in CPI (rural + urban) inflation starting 2017 for the entire basket of products combined.
A2: Qa. Create a graph depicting the growth rate Y-o-Y and identify the year with highest inflation rate
A3: (Rural+Urban) | G3: Rural | M3: Urban
A4: Years | B4: Jan | C4: Dec | D4: YoY% Change | G4: Years | H4: Jan | I4: Dec | J4: YoY%Change | M4: Years | N4: Jan | O4: Dec | P4: YoY%Change
A5: 2017 | B5: 130.3 | C5: 137.2 | D5: =(C5-B5)/B5 -> 0.05295472 | G5: 2017 | H5: 132.4 | I5: 139.8 | J5: =(I5-H5)/H5 -> 0.055891239 | M5: 2017 | N5: 127.8 | O5: 134.1 | P5: =(O5-N5)/N5 -> 0.049295775
A6: =A5+1 -> 2018 | B6: 136.9 | C6: 140.1 | D6: =(C6-B6)/B6 -> 0.023374726 | G6: =G5+1 -> 2018 | H6: 139.3 | I6: 141.9 | J6: =(I6-H6)/H6 -> 0.018664752 | M6: =M5+1 -> 2018 | N6: 134.1 | O6: 138 | P6: =(O6-N6)/N6 -> 0.029082774
A7: =A6+1 -> 2019 | B7: 139.6 | C7: 150.4 | D7: =(C7-B7)/B7 -> 0.077363897 | G7: =G6+1 -> 2019 | H7: 141 | I7: 152.3 | J7: =(I7-H7)/H7 -> 0.080141844 | M7: =M6+1 -> 2019 | N7: 138 | O7: 148.3 | P7: =(O7-N7)/N7 -> 0.074637681
A8: =A7+1 -> 2020 | B8: 150.2 | C8: 158.9 | D8: =(C8-B8)/B8 -> 0.05792277 | G8: =G7+1 -> 2020 | H8: 151.9 | I8: 160.7 | J8: =(I8-H8)/H8 -> 0.057932851 | M8: =M7+1 -> 2020 | N8: 148.2 | O8: 156.9 | P8: =(O8-N8)/N8 -> 0.058704453
A9: =A8+1 -> 2021 | B9: 157.3 | C9: 166.2 | D9: =(C9-B9)/B9 -> 0.056579784 | G9: =G8+1 -> 2021 | H9: 158.5 | I9: 167 | J9: =(I9-H9)/H9 -> 0.05362776 | M9: =M8+1 -> 2021 | N9: 156 | O9: 165.2 | P9: =(O9-N9)/N9 -> 0.058974359
A10: =A9+1 -> 2022 | B10: 165.7 | C10: 175.7 | D10: =(C10-B10)/B10 -> 0.06035003 | G10: =G9+1 -> 2022 | H10: 166.4 | I10: 177.1 | J10: =(I10-H10)/H10 -> 0.064302885 | M10: =M9+1 -> 2022 | N10: 165 | O10: 174.1 | P10: =(O10-N10)/N10 -> 0.055151515
A11: =A10+1 -> 2023 | B11: 176.5 | D11: We only have data till may 2023 | G11: =G10+1 -> 2023 | H11: 177.8 | J11: We only have data till may 2023 | M11: =M10+1 -> 2023 | N11: 174.9 | P11: We only have data till May 2023
A13: Highest Inflation in year 2019
A17: Qb. Highlight the reason why the year has the highest inflation (based on research)
A18: Rural+Urban
A19: Category Wise
A20: Food | F20: Miscellaneous | K20: Clothing | Q20: Housing | V20: Energy | AA20: Health
A21: Years | B21: Jan | C21: Dec | D21: YoY%Change | F21: Years | G21: Jan | H21: Dec | I21: YoY%Change | K21: Years | L21: Jan | M21: Dec | N21: YoY%Change | Q21: Years | R21: Jan | S21: Dec | T21: YoY%Change | V21: Years | W21: Jan | X21: Dec | Y21: YoY%Change | AA21: Years | AB21: Jan | AC21: Dec | AD21: YoY%Change
A22: 2017 | B22: ='Raw Data'!D148+'Raw Data'!E148+'Raw Data'!F148+'Raw Data'!G148++'Raw Data'!H148+'Raw Data'!I148+'Raw Data'!J148+'Raw Data'!K148+'Raw Data'!L148+'Raw Data'!M148+'Raw Data'!N148+'Raw Data'!O148+'Raw Data'!P148 -> 1727.3 | C22: =SUM('Raw Data'!D181:P181) -> 1795 | D22: =(C22-B22)/B22 -> 0.039194118 | F22: 2017 | G22: ='Raw Data'!Q148+'Raw Data'!Y148+'Raw Data'!Z148+'Raw Data'!AA148+'Raw Data'!AB148+'Raw Data'!AC148 -> 764.4 | H22: ='Raw Data'!Q181+'Raw Data'!Y181+'Raw Data'!Z181+'Raw Data'!AA181+'Raw Data'!AB181+'Raw Data'!AC181 -> 795.3 | I22: =(H22-G22)/G22 -> 0.040423862 | K22: 2017 | L22: =SUM('Raw Data'!R148:T148) -> 402.4 | M22: =SUM('Raw Data'!R181:T181) -> 420.2 | N22: =(M22-L22)/L22 -> 0.044234592 | Q22: 2017 | R22: ='Raw Data'!U148+'Raw Data'!W148 -> 259 | S22: ='Raw Data'!U181+'Raw Data'!W181 -> 273.8 | T22: =(S22-R22)/R22 -> 0.057142857 | V22: 2017 | W22: ='Raw Data'!V148 -> 126.8 | X22: ='Raw Data'!V181 -> 136.6 | Y22: =(X22-W22)/W22 -> 0.077287066 | AA22: 2017 | AB22: ='Raw Data'!X148 -> 127.1 | AC22: ='Raw Data'!X181 -> 133.1 | AD22: =(AC22-AB22)/AB22 -> 0.047206924
A23: =A22+1 -> 2018 | B23: ='Raw Data'!D184+'Raw Data'!E184+'Raw Data'!F184+'Raw Data'!G184+'Raw Data'!H184+'Raw Data'!I184+'Raw Data'!J184+'Raw Data'!K184+'Raw Data'!L184+'Raw Data'!M184+'Raw Data'!N184+'Raw Data'!O184+'Raw Data'!P184 -> 1779.9 | C23: =SUM('Raw Data'!D217:P217) -> 1762.8 | D23: =(C23-B23)/B23 -> -0.0096072813 | F23: =F22+1 -> 2018 | G23: ='Raw Data'!Q184+'Raw Data'!Y184+'Raw Data'!Z184+'Raw Data'!AA184+'Raw Data'!AB184+'Raw Data'!AC184 -> 799.1 | H23: ='Raw Data'!Q217+'Raw Data'!Y217+'Raw Data'!Z217+'Raw Data'!AA217+'Raw Data'!AB217+'Raw Data'!AC217 -> 842.5 | I23: =(H23-G23)/G23 -> 0.0543111 | K23: =K22+1 -> 2018 | L23: =SUM('Raw Data'!R184:T184) -> 421.3 | M23: =SUM('Raw Data'!R217:T217) -> 434.3 | N23: =(M23-L23)/L23 -> 0.030856872 | Q23: =Q22+1 -> 2018 | R23: ='Raw Data'!U184+'Raw Data'!W184 -> 275.3 | S23: ='Raw Data'!U217+'Raw Data'!W217 -> 289.7 | T23: =(S23-R23)/R23 -> 0.052306575 | V23: =V22+1 -> 2018 | W23: ='Raw Data'!V184 -> 136.6 | X23: ='Raw Data'!V217 -> 142.7 | Y23: =(X23-W23)/W23 -> 0.04465593 | AA23: =AA22+1 -> 2018 | AB23: ='Raw Data'!X184 -> 133.3 | AC23: ='Raw Data'!X217 -> 144.9 | AD23: =(AC23-AB23)/AB23 -> 0.087021755
A24: =A23+1 -> 2019 | B24: ='Raw Data'!D220+'Raw Data'!E220+'Raw Data'!F220+'Raw Data'!G220+'Raw Data'!H220+'Raw Data'!I220+'Raw Data'!J220+'Raw Data'!K220+'Raw Data'!L220+'Raw Data'!M220+'Raw Data'!N220+'Raw Data'!O220+'Raw Data'!P220 -> 1753.4 | C24: =SUM('Raw Data'!D250:P250) -> 1946.1 | D24: =(C24-B24)/B24 -> 0.10990076 | F24: =F23+1 -> 2019 | G24: ='Raw Data'!Q220+'Raw Data'!Y220+'Raw Data'!Z220+'Raw Data'!AA220+'Raw Data'!AB220+'Raw Data'!AC220 -> 843.1 | H24: ='Raw Data'!Q250+'Raw Data'!Y250+'Raw Data'!Z250+'Raw Data'!AA250+'Raw Data'!AB250+'Raw Data'!AC250 -> 879.2 | I24: =(H24-G24)/G24 -> 0.042818171 | K24: =K23+1 -> 2019 | L24: =SUM('Raw Data'!R220:T220) -> 433 | M24: =SUM('Raw Data'!R250:T250) -> 440.6 | N24: =(M24-L24)/L24 -> 0.017551963 | Q24: =Q23+1 -> 2019 | R24: ='Raw Data'!U220+'Raw Data'!W220 -> 291.3 | S24: ='Raw Data'!U250+'Raw Data'!W250 -> 298.6 | T24: =(S24-R24)/R24 -> 0.025060076 | V24: =V23+1 -> 2019 | W24: ='Raw Data'!V220 -> 139.5 | X24: ='Raw Data'!V250 -> 143.7 | Y24: =(X24-W24)/W24 -> 0.030107527 | AA24: =AA23+1 -> 2019 | AB24: ='Raw Data'!X220 -> 145.1 | AC24: ='Raw Data'!X250 -> 150.4 | AD24: =(AC24-AB24)/AB24 -> 0.036526533
A25: =A24+1 -> 2020 | B25: ='Raw Data'!D253+'Raw Data'!E253+'Raw Data'!F253+'Raw Data'!G253+'Raw Data'!H253+'Raw Data'!I253+'Raw Data'!J253+'Raw Data'!K253+'Raw Data'!L253+'Raw Data'!M253+'Raw Data'!N253+'Raw Data'!O253+'Raw Data'!P253 -> 1940.4 | C25: =SUM('Raw Data'!D286:P286) -> 2109.1 | D25: =(C25-B25)/B25 -> 0.086940837 | F25: =F24+1 -> 2020 | G25: ='Raw Data'!Q253+'Raw Data'!Y253+'Raw Data'!Z253+'Raw Data'!AA253+'Raw Data'!AB253+'Raw Data'!AC253 -> 884.7 | H25: ='Raw Data'!Q286+'Raw Data'!Y286+'Raw Data'!Z286+'Raw Data'!AA286+'Raw Data'!AB286+'Raw Data'!AC286 -> 942.3 | I25: =(H25-G25)/G25 -> 0.065106816 | K25: =K24+1 -> 2020 | L25: =SUM('Raw Data'!R253:T253) -> 441.2 | M25: =SUM('Raw Data'!R286:T286) -> 454 | N25: =(M25-L25)/L25 -> 0.029011786 | Q25: =Q24+1 -> 2020 | R25: ='Raw Data'!U253+'Raw Data'!W253 -> 300.1 | S25: ='Raw Data'!U286+'Raw Data'!W286 -> 308.1 | T25: =(S25-R25)/R25 -> 0.026657781 | V25: =V24+1 -> 2020 | W25: ='Raw Data'!V253 -> 144.6 | X25: ='Raw Data'!V286 -> 144.6 | Y25: =(X25-W25)/W25 -> 0 | AA25: =AA24+1 -> 2020 | AB25: ='Raw Data'!X253 -> 151.2 | AC25: ='Raw Data'!X286 -> 158.3 | AD25: =(AC25-AB25)/AB25 -> 0.046957672
A26: =A25+1 -> 2021 | B26: ='Raw Data'!D289+'Raw Data'!E289+'Raw Data'!F289+'Raw Data'!G289+'Raw Data'!H289+'Raw Data'!I289+'Raw Data'!J289+'Raw Data'!K289+'Raw Data'!L289+'Raw Data'!M289+'Raw Data'!N289+'Raw Data'!O289+'Raw Data'!P289 -> 2076.5 | C26: =SUM('Raw Data'!D322:P322) -> 2180.9 | D26: =(C26-B26)/B26 -> 0.050276908 | F26: =F25+1 -> 2021 | G26: ='Raw Data'!Q289+'Raw Data'!Y289+'Raw Data'!Z289+'Raw Data'!AA289+'Raw Data'!AB289+'Raw Data'!AC289 -> 945.9 | H26: ='Raw Data'!Q322+'Raw Data'!Y322+'Raw Data'!Z322+'Raw Data'!AA322+'Raw Data'!AB322+'Raw Data'!AC322 -> 997.7 | I26: =(H26-G26)/G26 -> 0.05476266 | K26: =K25+1 -> 2021 | L26: =SUM('Raw Data'!R289:T289) -> 455.8 | M26: =SUM('Raw Data'!R322:T322) -> 494.2 | N26: =(M26-L26)/L26 -> 0.084247477 | Q26: =Q25+1 -> 2021 | R26: ='Raw Data'!U289+'Raw Data'!W289 -> 307.7 | S26: ='Raw Data'!U322+'Raw Data'!W322 -> 323.6 | T26: =(S26-R26)/R26 -> 0.051673708 | V26: =V25+1 -> 2021 | W26: ='Raw Data'!V289 -> 147.9 | X26: ='Raw Data'!V322 -> 164.1 | Y26: =(X26-W26)/W26 -> 0.10953347 | AA26: =AA25+1 -> 2021 | AB26: ='Raw Data'!X289 -> 159.3 | AC26: ='Raw Data'!X322 -> 170.6 | AD26: =(AC26-AB26)/AB26 -> 0.070935342
A27: =A26+1 -> 2022 | B27: ='Raw Data'!D325+'Raw Data'!E325+'Raw Data'!F325+'Raw Data'!G325++'Raw Data'!H325+'Raw Data'!I325+'Raw Data'!J325+'Raw Data'!K325+'Raw Data'!L325+'Raw Data'!M325+'Raw Data'!N325+'Raw Data'!O325+'Raw Data'!P325 -> 2164.2 | C27: =SUM('Raw Data'!D358:P358) -> 2283.4 | D27: =(C27-B27)/B27 -> 0.055078089 | F27: =F26+1 -> 2022 | G27: ='Raw Data'!Q325+'Raw Data'!Y325+'Raw Data'!Z325+'Raw Data'!AA325+'Raw Data'!AB325+'Raw Data'!AC325 -> 1000.3 | H27: ='Raw Data'!Q358+'Raw Data'!Y358+'Raw Data'!Z358+'Raw Data'!AA358+'Raw Data'!AB358+'Raw Data'!AC358 -> 1051.5 | I27: =(H27-G27)/G27 -> 0.051184645 | K27: =K26+1 -> 2022 | L27: =SUM('Raw Data'!R325:T325) -> 499.1 | M27: =SUM('Raw Data'!R358:T358) -> 544 | N27: =(M27-L27)/L27 -> 0.089961931 | Q27: =Q26+1 -> 2022 | R27: ='Raw Data'!U325+'Raw Data'!W325 -> 325.6 | S27: ='Raw Data'!U358+'Raw Data'!W358 -> 342.8 | T27: =(S27-R27)/R27 -> 0.052825553 | V27: =V26+1 -> 2022 | W27: ='Raw Data'!V325 -> 164.2 | X27: ='Raw Data'!V358 -> 182 | Y27: =(X27-W27)/W27 -> 0.10840438 | AA27: =AA26+1 -> 2022 | AB27: ='Raw Data'!X325 -> 171.4 | AC27: ='Raw Data'!X358 -> 181.1 | AD27: =(AC27-AB27)/AB27 -> 0.056592765
A28: =A27+1 -> 2023 | B28: ='Raw Data'!D361+'Raw Data'!E361+'Raw Data'!F361+'Raw Data'!G361+'Raw Data'!H361+'Raw Data'!I361+'Raw Data'!J361+'Raw Data'!K361+'Raw Data'!L361+'Raw Data'!M361+'Raw Data'!N361+'Raw Data'!O361+'Raw Data'!P361 -> 2292.7 | D28: We only have data till may 2023 | F28: =F27+1 -> 2023 | G28: ='Raw Data'!Q361+'Raw Data'!Y361+'Raw Data'!Z361+'Raw Data'!AA361+'Raw Data'!AB361+'Raw Data'!AC361 -> 1057 | I28: We only have data till may 2023 | K28: =K27+1 -> 2023 | L28: =SUM('Raw Data'!R361:T361) -> 546.3 | N28: We only have data till may 2023 | Q28: =Q27+1 -> 2023 | R28: ='Raw Data'!U361+'Raw Data'!W361 -> 345 | T28: We only have data till may 2023 | V28: =V27+1 -> 2023 | W28: ='Raw Data'!V361 -> 182 | Y28: We only have data till may 2023 | AA28: =AA27+1 -> 2023 | AB28: ='Raw Data'!X361 -> 182.3 | AD28: We only have data till may 2023
A31: Urban
A32: Category Wise
A33: Food | F33: Miscellaneous | K33: Clothing | Q33: Housing | V33: Energy | AA33: Health
A34: Years | B34: Jan | C34: Dec | D34: YoY%Change | F34: Years | G34: Jan | H34: Dec | I34: YoY%Change | K34: Years | L34: Jan | M34: Dec | N34: YoY%Change | Q34: Years | R34: Jan | S34: Dec | T34: YoY%Change | V34: Years | W34: Jan | X34: Dec | Y34: YoY%Change | AA34: Years | AB34: Jan | AC34: Dec | AD34: YoY%Change
A35: 2017 | B35: =SUM('Raw Data'!D147:P147) -> 1713.2 | C35: =SUM('Raw Data'!D180:P180) -> 1767.5 | D35: =(C35-B35)/B35 -> 0.031695074 | F35: 2017 | G35: ='Raw Data'!Q147+'Raw Data'!Y147+'Raw Data'!Z147+'Raw Data'!AA147+'Raw Data'!AB147+'Raw Data'!AC147 -> 758.2 | H35: ='Raw Data'!Q180+'Raw Data'!Y180+'Raw Data'!Z180+'Raw Data'!AA180+'Raw Data'!AB180+'Raw Data'!AC180 -> 784.3 | I35: =(H35-G35)/G35 -> 0.034423635 | K35: 2017 | L35: =SUM('Raw Data'!R147:T147) -> 381.5 | M35: =SUM('Raw Data'!R180:T180) -> 395.2 | N35: =(M35-L35)/L35 -> 0.035910878 | Q35: 2017 | R35: ='Raw Data'!U147+'Raw Data'!W147 -> 254.7 | S35: ='Raw Data'!U180+'Raw Data'!W180 -> 268.4 | T35: =(S35-R35)/R35 -> 0.053788771 | V35: 2017 | W35: ='Raw Data'!V147 -> 118 | X35: ='Raw Data'!V180 -> 126.8 | Y35: =(X35-W35)/W35 -> 0.074576271 | AA35: 2017 | AB35: ='Raw Data'!X147 -> 122.6 | AC35: ='Raw Data'!X180 -> 128.2 | AD35: =(AC35-AB35)/AB35 -> 0.045676998
A36: =A35+1 -> 2018 | B36: =SUM('Raw Data'!D183:P183) -> 1748.3 | C36: =SUM('Raw Data'!D216:P216) -> 1746.6 | D36: =(C36-B36)/B36 -> -0.00097237316 | F36: =F35+1 -> 2018 | G36: ='Raw Data'!Q183+'Raw Data'!Y183+'Raw Data'!Z183+'Raw Data'!AA183+'Raw Data'!AB183+'Raw Data'!AC183 -> 788.6 | H36: ='Raw Data'!Q216+'Raw Data'!Y216+'Raw Data'!Z216+'Raw Data'!AA216+'Raw Data'!AB216+'Raw Data'!AC216 -> 824.1 | I36: =(H36-G36)/G36 -> 0.045016485 | K36: =K35+1 -> 2018 | L36: =SUM('Raw Data'!R183:T183) -> 396.3 | M36: =SUM('Raw Data'!R216:T216) -> 413.8 | N36: =(M36-L36)/L36 -> 0.044158466 | Q36: =Q35+1 -> 2018 | R36: ='Raw Data'!U183+'Raw Data'!W183 -> 269.9 | S36: ='Raw Data'!U216+'Raw Data'!W216 -> 282.7 | T36: =(S36-R36)/R36 -> 0.047424972 | V36: =V35+1 -> 2018 | W36: ='Raw Data'!V183 -> 127.3 | X36: ='Raw Data'!V216 -> 132.4 | Y36: =(X36-W36)/W36 -> 0.040062844 | AA36: =AA35+1 -> 2018 | AB36: ='Raw Data'!X183 -> 129 | AC36: ='Raw Data'!X216 -> 137.3 | AD36: =(AC36-AB36)/AB36 -> 0.064341085
A37: =A36+1 -> 2019 | B37: =SUM('Raw Data'!D219:P219) -> 1744.3 | C37: =SUM('Raw Data'!D249:P249) -> 1956.7 | D37: =(C37-B37)/B37 -> 0.12176804 | F37: =F36+1 -> 2019 | G37: ='Raw Data'!Q219+'Raw Data'!Y219+'Raw Data'!Z219+'Raw Data'!AA219+'Raw Data'!AB219+'Raw Data'!AC219 -> 825.3 | H37: ='Raw Data'!Q249+'Raw Data'!Y249+'Raw Data'!Z249+'Raw Data'!AA249+'Raw Data'!AB249+'Raw Data'!AC249 -> 862.2 | I37: =(H37-G37)/G37 -> 0.044711014 | K37: =K36+1 -> 2019 | L37: =SUM('Raw Data'!R219:T219) -> 414.5 | M37: =SUM('Raw Data'!R249:T249) -> 424.2 | N37: =(M37-L37)/L37 -> 0.023401689 | Q37: =Q36+1 -> 2019 | R37: ='Raw Data'!U219+'Raw Data'!W219 -> 284 | S37: ='Raw Data'!U249+'Raw Data'!W249 -> 292.6 | T37: =(S37-R37)/R37 -> 0.03028169 | V37: =V36+1 -> 2019 | W37: ='Raw Data'!V219 -> 128.6 | X37: ='Raw Data'!V249 -> 133.6 | Y37: =(X37-W37)/W37 -> 0.038880249 | AA37: =AA36+1 -> 2019 | AB37: ='Raw Data'!X219 -> 137.8 | AC37: ='Raw Data'!X249 -> 143.2 | AD37: =(AC37-AB37)/AB37 -> 0.039187228
A38: =A37+1 -> 2020 | B38: =SUM('Raw Data'!D252:P252) -> 1945.4 | C38: =SUM('Raw Data'!D285:P285) -> 2125.4 | D38: =(C38-B38)/B38 -> 0.092525959 | F38: =F37+1 -> 2020 | G38: ='Raw Data'!Q252+'Raw Data'!Y252+'Raw Data'!Z252+'Raw Data'!AA252+'Raw Data'!AB252+'Raw Data'!AC252 -> 866.7 | H38: ='Raw Data'!Q285+'Raw Data'!Y285+'Raw Data'!Z285+'Raw Data'!AA285+'Raw Data'!AB285+'Raw Data'!AC285 -> 931.7 | I38: =(H38-G38)/G38 -> 0.074997115 | K38: =K37+1 -> 2020 | L38: =SUM('Raw Data'!R252:T252) -> 425.1 | M38: =SUM('Raw Data'!R285:T285) -> 438.2 | N38: =(M38-L38)/L38 -> 0.030816279 | Q38: =Q37+1 -> 2020 | R38: ='Raw Data'!U252+'Raw Data'!W252 -> 294 | S38: ='Raw Data'!U285+'Raw Data'!W285 -> 303.9 | T38: =(S38-R38)/R38 -> 0.033673469 | V38: =V37+1 -> 2020 | W38: ='Raw Data'!V252 -> 135.1 | X38: ='Raw Data'!V285 -> 137.9 | Y38: =(X38-W38)/W38 -> 0.020725389 | AA38: =AA37+1 -> 2020 | AB38: ='Raw Data'!X252 -> 143.8 | AC38: ='Raw Data'!X285 -> 152.9 | AD38: =(AC38-AB38)/AB38 -> 0.063282337
A39: =A38+1 -> 2021 | B39: =SUM('Raw Data'!D288:P288) -> 2097 | C39: =SUM('Raw Data'!D321:P321) -> 2206.3 | D39: =(C39-B39)/B39 -> 0.052122079 | F39: =F38+1 -> 2021 | G39: ='Raw Data'!Q288++'Raw Data'!Y288+'Raw Data'!Z288+'Raw Data'!AA288+'Raw Data'!AB288+'Raw Data'!AC288 -> 935.5 | H39: ='Raw Data'!Q321+'Raw Data'!Y321+'Raw Data'!Z321+'Raw Data'!AA321+'Raw Data'!AB321+'Raw Data'!AC321 -> 987 | I39: =(H39-G39)/G39 -> 0.055050775 | K39: =K38+1 -> 2021 | L39: =SUM('Raw Data'!R288:T288) -> 440 | M39: =SUM('Raw Data'!R321:T321) -> 470.7 | N39: =(M39-L39)/L39 -> 0.069772727 | Q39: =Q38+1 -> 2021 | R39: ='Raw Data'!U288+'Raw Data'!W288 -> 303.4 | S39: ='Raw Data'!U321+'Raw Data'!W321 -> 319.4 | T39: =(S39-R39)/R39 -> 0.052735662 | V39: =V38+1 -> 2021 | W39: ='Raw Data'!V288 -> 142.9 | X39: ='Raw Data'!V321 -> 161.7 | Y39: =(X39-W39)/W39 -> 0.13156053 | AA39: =AA38+1 -> 2021 | AB39: ='Raw Data'!X288 -> 154.1 | AC39: ='Raw Data'!X321 -> 165.1 | AD39: =(AC39-AB39)/AB39 -> 0.071382219
A40: =A39+1 -> 2022 | B40: =SUM('Raw Data'!D324:P324) -> 2186.7 | C40: =SUM('Raw Data'!D357:P357) -> 2295.8 | D40: =(C40-B40)/B40 -> 0.049892532 | F40: =F39+1 -> 2022 | G40: ='Raw Data'!Q324+'Raw Data'!Y324+'Raw Data'!Z324+'Raw Data'!AA324+'Raw Data'!AB324+'Raw Data'!AC324 -> 989.9 | H40: ='Raw Data'!Q357+'Raw Data'!Y357+'Raw Data'!Z357+'Raw Data'!AA357+'Raw Data'!AB357+'Raw Data'!AC357 -> 1043.6 | I40: =(H40-G40)/G40 -> 0.054247904 | K40: =K39+1 -> 2022 | L40: =SUM('Raw Data'!R324:T324) -> 475.4 | M40: =SUM('Raw Data'!R357:T357) -> 517.9 | N40: =(M40-L40)/L40 -> 0.089398401 | Q40: =Q39+1 -> 2022 | R40: ='Raw Data'!U324+'Raw Data'!W324 -> 321.3 | S40: ='Raw Data'!U357+'Raw Data'!W357 -> 338 | T40: =(S40-R40)/R40 -> 0.051976346 | V40: =V39+1 -> 2022 | W40: ='Raw Data'!V324 -> 161.6 | X40: ='Raw Data'!V357 -> 180.6 | Y40: =(X40-W40)/W40 -> 0.11757426 | AA40: =AA39+1 -> 2022 | AB40: ='Raw Data'!X324 -> 166.1 | AC40: ='Raw Data'!X357 -> 177.2 | AD40: =(AC40-AB40)/AB40 -> 0.066827213
A41: =A40+1 -> 2023 | B41: =SUM('Raw Data'!D360:P360) -> 2310.2 | D41: We only have data till may 2023 | F41: =F40+1 -> 2023 | G41: ='Raw Data'!Q360+'Raw Data'!Y360+'Raw Data'!Z360+'Raw Data'!AA360+'Raw Data'!AB360+'Raw Data'!AC360 -> 1048.4 | I41: We only have data till may 2023 | K41: =K40+1 -> 2023 | L41: =SUM('Raw Data'!R360:T360) -> 520.6 | N41: We only have data till may 2023 | Q41: =Q40+1 -> 2023 | R41: ='Raw Data'!U360+'Raw Data'!W360 -> 340.1 | T41: We only have data till may 2023 | V41: =V40+1 -> 2023 | W41: ='Raw Data'!V360 -> 180.1 | Y41: We only have data till may 2023 | AA41: =AA40+1 -> 2023 | AB41: ='Raw Data'!X360 -> 178.5 | AD41: We only have data till may 2023
A45: Rural
A46: Category Wise
A47: Food | F47: Miscellaneous | K47: Clothing | Q47: Housing | V47: Energy | AA47: Health
A48: Years | B48: Jan | C48: Dec | D48: YoY%Change | F48: Years | G48: Jan | H48: Dec | I48: YoY%Change | K48: Years | L48: Jan | M48: Dec | N48: YoY%Change | Q48: Years | R48: Jan | S48: Dec | T48: YoY%Change | V48: Years | W48: Jan | X48: Dec | Y48: YoY%Change | AA48: Years | AB48: Jan | AC48: Dec | AD48: YoY%Change
A49: 2017 | B49: =SUM('Raw Data'!D146:P146) -> 1737.3 | C49: =SUM('Raw Data'!D179:P179) -> 1813.6 | D49: =(C49-B49)/B49 -> 0.043918724 | F49: 2017 | G49: ='Raw Data'!Q146+'Raw Data'!Y146+'Raw Data'!Z146+'Raw Data'!AA146+'Raw Data'!AB146+'Raw Data'!AC146 -> 772.7 | H49: ='Raw Data'!Q179+'Raw Data'!Y179+'Raw Data'!Z179+'Raw Data'!AA179+'Raw Data'!AB179+'Raw Data'!AC179 -> 809.4 | I49: =(H49-G49)/G49 -> 0.047495794 | K49: 2017 | L49: =SUM('Raw Data'!R146:T146) -> 416.5 | M49: =SUM('Raw Data'!R179:T179) -> 437.1 | N49: =(M49-L49)/L49 -> 0.049459784 | Q49: 2017 | R49: ='Raw Data'!U147+'Raw Data'!W147 -> 254.7 | S49: ='Raw Data'!U180+'Raw Data'!W180 -> 268.4 | T49: =(S49-R49)/R49 -> 0.053788771 | V49: 2017 | W49: ='Raw Data'!V146 -> 132.1 | X49: ='Raw Data'!V179 -> 142.6 | Y49: =(X49-W49)/W49 -> 0.079485238 | AA49: 2017 | AB49: ='Raw Data'!X146 -> 129.9 | AC49: ='Raw Data'!X179 -> 136.1 | AD49: =(AC49-AB49)/AB49 -> 0.047729022
A50: =A49+1 -> 2018 | B50: =SUM('Raw Data'!D182:P182) -> 1800.7 | C50: =SUM('Raw Data'!D215:P215) -> 1773.1 | D50: =(C50-B50)/B50 -> -0.015327373 | F50: =F49+1 -> 2018 | G50: ='Raw Data'!Q182+'Raw Data'!Y182+'Raw Data'!Z182+'Raw Data'!AA182+'Raw Data'!AB182+'Raw Data'!AC182 -> 813.1 | H50: ='Raw Data'!Q215+'Raw Data'!Y215+'Raw Data'!Z215+'Raw Data'!AA215+'Raw Data'!AB215+'Raw Data'!AC215 -> 864.5 | I50: =(H50-G50)/G50 -> 0.063214857 | K50: =K49+1 -> 2018 | L50: =SUM('Raw Data'!R182:T182) -> 438.1 | M50: =SUM('Raw Data'!R215:T215) -> 448.3 | N50: =(M50-L50)/L50 -> 0.023282356 | Q50: =Q49+1 -> 2018 | R50: ='Raw Data'!U183+'Raw Data'!W183 -> 269.9 | S50: ='Raw Data'!U216+'Raw Data'!W216 -> 282.7 | T50: =(S50-R50)/R50 -> 0.047424972 | V50: =V49+1 -> 2018 | W50: ='Raw Data'!V182 -> 142.3 | X50: ='Raw Data'!V215 -> 149 | Y50: =(X50-W50)/W50 -> 0.047083626 | AA50: =AA49+1 -> 2018 | AB50: ='Raw Data'!X182 -> 136 | AC50: ='Raw Data'!X215 -> 149.6 | AD50: =(AC50-AB50)/AB50 -> 0.1
A51: =A50+1 -> 2019 | B51: =SUM('Raw Data'!D218:P218) -> 1759.6 | C51: =SUM('Raw Data'!D248:P248) -> 1941 | D51: =(C51-B51)/B51 -> 0.10309161 | F51: =F50+1 -> 2019 | G51: ='Raw Data'!Q218+'Raw Data'!Y218+'Raw Data'!Z218+'Raw Data'!AA218+'Raw Data'!AB218+'Raw Data'!AC218 -> 864.6 | H51: ='Raw Data'!Q248+'Raw Data'!Y248+'Raw Data'!Z248+'Raw Data'!AA248+'Raw Data'!AB248+'Raw Data'!AC248 -> 901.1 | I51: =(H51-G51)/G51 -> 0.042216054 | K51: =K50+1 -> 2019 | L51: =SUM('Raw Data'!R218:T218) -> 445.6 | M51: =SUM('Raw Data'!R248:T248) -> 451.8 | N51: =(M51-L51)/L51 -> 0.013913824 | Q51: =Q50+1 -> 2019 | R51: ='Raw Data'!U219+'Raw Data'!W219 -> 284 | S51: ='Raw Data'!U249+'Raw Data'!W249 -> 292.6 | T51: =(S51-R51)/R51 -> 0.03028169 | V51: =V50+1 -> 2019 | W51: ='Raw Data'!V218 -> 146.2 | X51: ='Raw Data'!V248 -> 149.9 | Y51: =(X51-W51)/W51 -> 0.025307798 | AA51: =AA50+1 -> 2019 | AB51: ='Raw Data'!X218 -> 149.6 | AC51: ='Raw Data'!X248 -> 154.8 | AD51: =(AC51-AB51)/AB51 -> 0.034759358
A52: =A51+1 -> 2020 | B52: =SUM('Raw Data'!D251:P251) -> 1938.6 | C52: =SUM('Raw Data'!D284:P284) -> 2100.5 | D52: =(C52-B52)/B52 -> 0.083513876 | F52: =F51+1 -> 2020 | G52: ='Raw Data'!Q251+'Raw Data'!Y251+'Raw Data'!Z251+'Raw Data'!AA251+'Raw Data'!AB251+'Raw Data'!AC251 -> 907.3 | H52: ='Raw Data'!Q284+'Raw Data'!Y284+'Raw Data'!Z284+'Raw Data'!AA284+'Raw Data'!AB284+'Raw Data'!AC284 -> 958.6 | I52: =(H52-G52)/G52 -> 0.056541387 | K52: =K51+1 -> 2020 | L52: =SUM('Raw Data'!R251:T251) -> 452.3 | M52: =SUM('Raw Data'!R284:T284) -> 464.9 | N52: =(M52-L52)/L52 -> 0.027857617 | Q52: =Q51+1 -> 2020 | R52: ='Raw Data'!U252+'Raw Data'!W252 -> 294 | S52: ='Raw Data'!U285+'Raw Data'!W285 -> 303.9 | T52: =(S52-R52)/R52 -> 0.033673469 | V52: =V51+1 -> 2020 | W52: ='Raw Data'!V251 -> 150.4 | X52: ='Raw Data'!V284 -> 148.7 | Y52: =(X52-W52)/W52 -> -0.011303191 | AA52: =AA51+1 -> 2020 | AB52: ='Raw Data'!X251 -> 155.7 | AC52: ='Raw Data'!X284 -> 161.6 | AD52: =(AC52-AB52)/AB52 -> 0.037893385
A53: =A52+1 -> 2021 | B53: =SUM('Raw Data'!D287:P287) -> 2065.7 | C53: =SUM('Raw Data'!D320:P320) -> 2168.2 | D53: =(C53-B53)/B53 -> 0.049619984 | F53: =F52+1 -> 2021 | G53: ='Raw Data'!Q287+'Raw Data'!Y287+'Raw Data'!Z287+'Raw Data'!AA287+'Raw Data'!AB287+'Raw Data'!AC287 -> 962.8 | H53: ='Raw Data'!Q320+'Raw Data'!Y320+'Raw Data'!Z320+'Raw Data'!AA320+'Raw Data'!AB320+'Raw Data'!AC320 -> 1013.9 | I53: =(H53-G53)/G53 -> 0.053074366 | K53: =K52+1 -> 2021 | L53: =SUM('Raw Data'!R287:T287) -> 466.7 | M53: =SUM('Raw Data'!R320:T320) -> 510.3 | N53: =(M53-L53)/L53 -> 0.093421898 | Q53: =Q52+1 -> 2021 | R53: ='Raw Data'!U288+'Raw Data'!W288 -> 303.4 | S53: ='Raw Data'!U321+'Raw Data'!W321 -> 319.4 | T53: =(S53-R53)/R53 -> 0.052735662 | V53: =V52+1 -> 2021 | W53: ='Raw Data'!V287 -> 150.9 | X53: ='Raw Data'!V320 -> 165.6 | Y53: =(X53-W53)/W53 -> 0.097415507 | AA53: =AA52+1 -> 2021 | AB53: ='Raw Data'!X287 -> 162.5 | AC53: ='Raw Data'!X320 -> 174 | AD53: =(AC53-AB53)/AB53 -> 0.070769231
A54: =A53+1 -> 2022 | B54: =SUM('Raw Data'!D323:P323) -> 2153 | C54: =SUM('Raw Data'!D356:P356) -> 2277.1 | D54: =(C54-B54)/B54 -> 0.057640502 | F54: =F53+1 -> 2022 | G54: ='Raw Data'!Q323+'Raw Data'!Y323+'Raw Data'!Z323+'Raw Data'!AA323+'Raw Data'!AB323+'Raw Data'!AC323 -> 1016.1 | H54: ='Raw Data'!Q356+'Raw Data'!Y356+'Raw Data'!Z356+'Raw Data'!AA356+'Raw Data'!AB356+'Raw Data'!AC356 -> 1063.4 | I54: =(H54-G54)/G54 -> 0.046550536 | K54: =K53+1 -> 2022 | L54: =SUM('Raw Data'!R323:T323) -> 515.2 | M54: =SUM('Raw Data'!R356:T356) -> 561.8 | N54: =(M54-L54)/L54 -> 0.090450311 | Q54: =Q53+1 -> 2022 | R54: ='Raw Data'!U324+'Raw Data'!W324 -> 321.3 | S54: ='Raw Data'!U357+'Raw Data'!W357 -> 338 | T54: =(S54-R54)/R54 -> 0.051976346 | V54: =V53+1 -> 2022 | W54: ='Raw Data'!V323 -> 165.8 | X54: ='Raw Data'!V356 -> 182.8 | Y54: =(X54-W54)/W54 -> 0.10253317 | AA54: =AA53+1 -> 2022 | AB54: ='Raw Data'!X323 -> 174.7 | AC54: ='Raw Data'!X356 -> 183.5 | AD54: =(AC54-AB54)/AB54 -> 0.050372066
A55: =A54+1 -> 2023 | B55: =SUM('Raw Data'!D359:P359) -> 2283.2 | D55: We only have data till may 2023 | F55: =F54+1 -> 2023 | G55: ='Raw Data'!Q359+'Raw Data'!Y359+'Raw Data'!Z359+'Raw Data'!AA359+'Raw Data'!AB359+'Raw Data'!AC359 -> 1069.6 | I55: We only have data till may 2023 | K55: =K54+1 -> 2023 | L55: =SUM('Raw Data'!R359:T359) -> 563.9 | N55: We only have data till may 2023 | Q55: =Q54+1 -> 2023 | R55: ='Raw Data'!U360+'Raw Data'!W360 -> 340.1 | T55: We only have data till may 2023 | V55: =V54+1 -> 2023 | W55: ='Raw Data'!V359 -> 183.2 | Y55: We only have data till may 2023 | AA55: =AA54+1 -> 2023 | AB55: ='Raw Data'!X359 -> 184.7 | AD55: We only have data till may 2023
Q56: (we used the same data as the urban data as we did
Q57: not have enough data in rural sector)

Sheet PS3
A1: 3. With India's retail inflation reaching a 3-month high of 5.55% in November 2023, largely due to a sharp rise in food prices. Analyze the following for 12 months ending May’23
A2: Investigate trends in the prices of broader food bucket category and evaluate month-on-month changes. Highlight month with highest and lowest food inflation
A3: The time frame is between June 22 to May 23.
A4: Rural
A5: Category wise (Food)
A6: Year | B6: Month | C6: CPI(Food) | D6: MoM% | E6: Cereals and products | F6: Meat and fish | G6: Egg | H6: Milk and products | I6: Oils and fats | J6: Fruits | K6: Vegetables | L6: Pulses and products | M6: Sugar and Confectionery | N6: Spices | O6: Non-alcoholic beverages | P6: Prepared meals, snacks, sweets etc. | Q6: Food and beverages
A7: 2022 | B7: May | C7: =SUM('Raw Data'!D335:P335) -> 2226.8 | E7: 152.9 | F7: 214.7 | G7: 161.4 | H7: 164.6 | I7: 209.9 | J7: 168 | K7: 160.4 | L7: 165 | M7: 118.9 | N7: 186.6 | O7: 173.2 | P7: 180.4 | Q7: 170.8
A8: 2022 | B8: June | C8: =SUM('Raw Data'!D338:P338) -> 2248.3 | D8: =(C8-C7)/C7 -> 0.0096551105 | E8: 153.8 | F8: 217.2 | G8: 169.6 | H8: 165.4 | I8: 208.1 | J8: 165.8 | K8: 167.3 | L8: 164.6 | M8: 119.1 | N8: 188.9 | O8: 174.2 | P8: 181.9 | Q8: 172.4
A9: 2022 | B9: July | C9: =SUM('Raw Data'!D341:P341) -> 2252.5 | D9: =(C9-C8)/C8 -> 0.0018680781 | E9: 155.2 | F9: 210.8 | G9: 174.3 | H9: 166.3 | I9: 202.2 | J9: 169.6 | K9: 168.6 | L9: 164.4 | M9: 119.2 | N9: 191.8 | O9: 174.5 | P9: 183.1 | Q9: 172.5
A10: 2022 | B10: August | C10: =SUM('Raw Data'!D344:P344) -> 2255.8 | D10: =(C10-C9)/C9 -> 0.0014650388 | E10: 159.5 | F10: 204.1 | G10: 168.3 | H10: 167.9 | I10: 198.1 | J10: 169.2 | K10: 173.1 | L10: 167.1 | M10: 120.2 | N10: 195.6 | O10: 174.8 | P10: 184 | Q10: 173.9
A11: 2022 | B11: September | C11: =SUM('Raw Data'!D347:P347) -> 2267.8 | D11: =(C11-C10)/C10 -> 0.0053196205 | E11: 162.9 | F11: 206.7 | G11: 169 | H11: 169.5 | I11: 194.1 | J11: 164.1 | K11: 176.9 | L11: 169 | M11: 120.8 | N11: 199.1 | O11: 175.4 | P11: 184.8 | Q11: 175.5
A12: 2022 | B12: October | C12: =SUM('Raw Data'!D350:P350) -> 2284.5 | D12: =(C12-C11)/C11 -> 0.0073639651 | E12: 164.7 | F12: 208.8 | G12: 170.3 | H12: 170.9 | I12: 191.6 | J12: 162.2 | K12: 184.8 | L12: 169.7 | M12: 121.1 | N12: 201.6 | O12: 175.8 | P12: 185.6 | Q12: 177.4
A13: 2022 | B13: November | C13: =SUM('Raw Data'!D353:P353) -> 2287.7 | D13: =(C13-C12)/C12 -> 0.0014007441 | E13: 166.9 | F13: 207.2 | G13: 180.2 | H13: 172.3 | I13: 194 | J13: 159.1 | K13: 171.6 | L13: 170.2 | M13: 121.5 | N13: 204.8 | O13: 176.4 | P13: 186.9 | Q13: 176.6
A14: 2022 | B14: December | C14: =SUM('Raw Data'!D356:P356) -> 2277.1 | D14: =(C14-C13)/C13 -> -0.0046334747 | E14: 168.8 | F14: 206.9 | G14: 189.1 | H14: 173.4 | I14: 193.9 | J14: 156.7 | K14: 150.2 | L14: 170.5 | M14: 121.2 | N14: 207.5 | O14: 176.8 | P14: 187.7 | Q14: 174.4
A15: 2023 | B15: January | C15: =SUM('Raw Data'!D359:P359) -> 2283.2 | D15: =(C15-C14)/C14 -> 0.0026788459 | E15: 174 | F15: 208.3 | G15: 192.9 | H15: 174.3 | I15: 192.6 | J15: 156.3 | K15: 142.9 | L15: 170.7 | M15: 120.3 | N15: 210.5 | O15: 176.9 | P15: 188.5 | Q15: 175
A16: 2023 | B16: February | C16: =SUM('Raw Data'!D362:P362) -> 2265.7 | D16: =(C16-C15)/C15 -> -0.0076646811 | E16: 174.2 | F16: 205.2 | G16: 173.9 | H16: 177 | I16: 183.4 | J16: 167.2 | K16: 140.9 | L16: 170.4 | M16: 119.1 | N16: 212.1 | O16: 177.6 | P16: 189.9 | Q16: 174.8
A17: 2023 | B17: March | C17: =SUM('Raw Data'!D365:P365) -> 2265.8 | D17: =(C17-C16)/C16 -> 4.413647e-05 | E17: 174.3 | F17: 205.2 | G17: 173.9 | H17: 177 | I17: 183.3 | J17: 167.2 | K17: 140.9 | L17: 170.5 | M17: 119.1 | N17: 212.1 | O17: 177.6 | P17: 189.9 | Q17: 174.8
A18: 2023 | B18: April | C18: =SUM('Raw Data'!D368:P368) -> 2274.2 | D18: =(C18-C17)/C17 -> 0.0037072998 | E18: 173.3 | F18: 206.9 | G18: 167.9 | H18: 178.2 | I18: 178.5 | J18: 173.7 | K18: 142.8 | L18: 172.8 | M18: 120.4 | N18: 215.5 | O18: 178.2 | P18: 190.5 | Q18: 175.5
A19: 2023 | B19: May | C19: =SUM('Raw Data'!D371:P371) -> 2290.7 | D19: =(C19-C18)/C18 -> 0.0072552986 | E19: 173.2 | F19: 211.5 | G19: 171 | H19: 179.6 | I19: 173.3 | J19: 169 | K19: 148.7 | L19: 174.9 | M19: 121.9 | N19: 221 | O19: 178.7 | P19: 191.1 | Q19: 176.8
A22: Urban
A23: Category wise (Food)
A24: Year | B24: Month | C24: CPI(Food) | D24: MoM% | E24: Cereals and products | F24: Meat and fish | G24: Egg | H24: Milk and products | I24: Oils and fats | J24: Fruits | K24: Vegetables | L24: Pulses and products | M24: Sugar and Confectionery | N24: Spices | O24: Non-alcoholic beverages | P24: Prepared meals, snacks, sweets etc. | Q24: Food and beverages
A25: 2022 | B25: May | C25: =SUM(E25:Q25) -> 2262.2 | E25: 156.7 | F25: 221.2 | G25: 164.1 | H25: 165.4 | I25: 189.5 | J25: 174.5 | K25: 203.2 | L25: 164.1 | M25: 121.2 | N25: 181.4 | O25: 158.5 | P25: 184.9 | Q25: 177.5
A26: 2022 | B26: June | C26: =SUM(E26:Q26) -> 2287.5 | D26: =(C26-C25)/C25 -> 0.011183803 | E26: 157.5 | F26: 223.4 | G26: 172.8 | H26: 166.4 | I26: 188.6 | J26: 174.1 | K26: 211.5 | L26: 163.6 | M26: 121.4 | N26: 183.5 | O26: 159.1 | P26: 186.3 | Q26: 179.3
A27: 2022 | B27: July | C27: =SUM(E27:Q27) -> 2291.6 | D27: =(C27-C26)/C26 -> 0.0017923497 | E27: 159.3 | F27: 217.1 | G27: 176.6 | H27: 167.1 | I27: 184.8 | J27: 179.5 | K27: 208.5 | L27: 164 | M27: 121.5 | N27: 186.3 | O27: 159.8 | P27: 187.7 | Q27: 179.4
A28: 2022 | B28: August | C28: =SUM(E28:Q28) -> 2293.7 | D28: =(C28-C27)/C27 -> 0.00091639029 | E28: 162.1 | F28: 210.9 | G28: 170.6 | H28: 168.4 | I28: 182.5 | J28: 177.1 | K28: 213.1 | L28: 167.3 | M28: 122.2 | N28: 189.7 | O28: 160.5 | P28: 188.9 | Q28: 180.4
A29: 2022 | B29: September | C29: =SUM(E29:Q29) -> 2306.4 | D29: =(C29-C28)/C28 -> 0.0055369054 | E29: 164.9 | F29: 213.7 | G29: 170.9 | H29: 170.1 | I29: 179.3 | J29: 167.5 | K29: 220.8 | L29: 169.2 | M29: 123.1 | N29: 193.6 | O29: 161.1 | P29: 190.4 | Q29: 181.8
A30: 2022 | B30: October | C30: =SUM(E30:Q30) -> 2322.3 | D30: =(C30-C29)/C29 -> 0.0068938606 | E30: 166.4 | F30: 214.9 | G30: 171.9 | H30: 171 | I30: 177.7 | J30: 165.7 | K30: 228.6 | L30: 169.9 | M30: 123.4 | N30: 196.4 | O30: 161.6 | P30: 191.5 | Q30: 183.3
A31: 2022 | B31: November | C31: =SUM(E31:Q31) -> 2314.4 | D31: =(C31-C30)/C30 -> -0.0034017999 | E31: 168.4 | F31: 213.4 | G31: 183.2 | H31: 172.3 | I31: 180 | J31: 162.6 | K31: 205.5 | L31: 171 | M31: 123.4 | N31: 198.8 | O31: 162.1 | P31: 192.4 | Q31: 181.3
A32: 2022 | B32: December | C32: =SUM(E32:Q32) -> 2295.8 | D32: =(C32-C31)/C31 -> -0.0080366402 | E32: 170.2 | F32: 212.9 | G32: 191.9 | H32: 173.9 | I32: 179.1 | J32: 159.5 | K32: 178.7 | L32: 171.3 | M32: 123.1 | N32: 200.5 | O32: 162.8 | P32: 193.3 | Q32: 178.6
A33: 2023 | B33: January | C33: =SUM(E33:Q33) -> 2310.2 | D33: =(C33-C32)/C32 -> 0.0062723234 | E33: 173.3 | F33: 215.2 | G33: 197 | H33: 175.2 | I33: 178 | J33: 160.5 | K33: 175.3 | L33: 171.2 | M33: 122.7 | N33: 204.3 | O33: 163.7 | P33: 194.3 | Q33: 179.5
A34: 2023 | B34: February | C34: =SUM(E34:Q34) -> 2303.2 | D34: =(C34-C33)/C33 -> -0.0030300407 | E34: 174.7 | F34: 212.2 | G34: 177.2 | H34: 177.9 | I34: 172.2 | J34: 172.1 | K34: 175.8 | L34: 172.2 | M34: 121.9 | N34: 204.8 | O34: 164.9 | P34: 196.6 | Q34: 180.7
A35: 2023 | B35: March | C35: =SUM(E35:Q35) -> 2303.4 | D35: =(C35-C34)/C34 -> 8.6835707e-05 | E35: 174.7 | F35: 212.2 | G35: 177.2 | H35: 177.9 | I35: 172.2 | J35: 172.1 | K35: 175.9 | L35: 172.2 | M35: 121.9 | N35: 204.8 | O35: 164.9 | P35: 196.6 | Q35: 180.8
A36: 2023 | B36: April | C36: =SUM(E36:Q36) -> 2317.7 | D36: =(C36-C35)/C35 -> 0.0062082139 | E36: 174.8 | F36: 213.7 | G36: 172.4 | H36: 178.8 | I36: 168.7 | J36: 179.2 | K36: 179.9 | L36: 174.7 | M36: 123.1 | N36: 207.8 | O36: 165.5 | P36: 197 | Q36: 182.1
A37: 2023 | B37: May | C37: =SUM(E37:Q37) -> 2335.1 | D37: =(C37-C36)/C36 -> 0.0075074427 | E37: 174.7 | F37: 219.4 | G37: 176.7 | H37: 179.4 | I37: 164.4 | J37: 175.8 | K37: 185 | L37: 176.9 | M37: 124.2 | N37: 211.9 | O37: 165.9 | P37: 197.7 | Q37: 183.1
A40: Rural+Urban
A41: Category wise (Food)
A42: Year | B42: Month | C42: CPI(Food) | D42: MoM% | E42: Cereals and products | F42: Meat and fish | G42: Egg | H42: Milk and products | I42: Oils and fats | J42: Fruits | K42: Vegetables | L42: Pulses and products | M42: Sugar and Confectionery | N42: Spices | O42: Non-alcoholic beverages | P42: Prepared meals, snacks, sweets etc. | Q42: Food and beverages
A43: 2022 | B43: May | C43: =SUM(E43:Q43) -> 2238.9 | E43: 154.1 | F43: 217 | G43: 162.4 | H43: 164.9 | I43: 202.4 | J43: 171 | K43: 174.9 | L43: 164.7 | M43: 119.7 | N43: 184.9 | O43: 167.1 | P43: 182.5 | Q43: 173.3
A44: 2022 | B44: June | C44: =SUM(E44:Q44) -> 2261.9 | D44: =(C44-C43)/C43 -> 0.010272902 | E44: 155 | F44: 219.4 | G44: 170.8 | H44: 165.8 | I44: 200.9 | J44: 169.7 | K44: 182.3 | L44: 164.3 | M44: 119.9 | N44: 187.1 | O44: 167.9 | P44: 183.9 | Q44: 174.9
A45: 2022 | B45: July | C45: =SUM(E45:Q45) -> 2266.3 | D45: =(C45-C44)/C44 -> 0.0019452673 | E45: 156.5 | F45: 213 | G45: 175.2 | H45: 166.6 | I45: 195.8 | J45: 174.2 | K45: 182.1 | L45: 164.3 | M45: 120 | N45: 190 | O45: 168.4 | P45: 185.2 | Q45: 175
A46: 2022 | B46: August | C46: =SUM(E46:Q46) -> 2269.2 | D46: =(C46-C45)/C45 -> 0.0012796188 | E46: 160.3 | F46: 206.5 | G46: 169.2 | H46: 168.1 | I46: 192.4 | J46: 172.9 | K46: 186.7 | L46: 167.2 | M46: 120.9 | N46: 193.6 | O46: 168.8 | P46: 186.3 | Q46: 176.3
A47: 2022 | B47: September | C47: =SUM(E47:Q47) -> 2280.9 | D47: =(C47-C46)/C46 -> 0.0051560021 | E47: 163.5 | F47: 209.2 | G47: 169.7 | H47: 169.7 | I47: 188.7 | J47: 165.7 | K47: 191.8 | L47: 169.1 | M47: 121.6 | N47: 197.3 | O47: 169.4 | P47: 187.4 | Q47: 177.8
A48: 2022 | B48: October | C48: =SUM(E48:Q48) -> 2297.3 | D48: =(C48-C47)/C47 -> 0.0071901442 | E48: 165.2 | F48: 210.9 | G48: 170.9 | H48: 170.9 | I48: 186.5 | J48: 163.8 | K48: 199.7 | L48: 169.8 | M48: 121.9 | N48: 199.9 | O48: 169.9 | P48: 188.3 | Q48: 179.6
A49: 2022 | B49: November | C49: =SUM(E49:Q49) -> 2296.8 | D49: =(C49-C48)/C48 -> -0.0002176468 | E49: 167.4 | F49: 209.4 | G49: 181.4 | H49: 172.3 | I49: 188.9 | J49: 160.7 | K49: 183.1 | L49: 170.5 | M49: 122.1 | N49: 202.8 | O49: 170.4 | P49: 189.5 | Q49: 178.3
A50: 2022 | B50: December | C50: =SUM(E50:Q50) -> 2283.4 | D50: =(C50-C49)/C49 -> -0.0058342041 | E50: 169.2 | F50: 209 | G50: 190.2 | H50: 173.6 | I50: 188.5 | J50: 158 | K50: 159.9 | L50: 170.8 | M50: 121.8 | N50: 205.2 | O50: 171 | P50: 190.3 | Q50: 175.9
A51: 2023 | B51: January | C51: =SUM(E51:Q51) -> 2292.7 | D51: =(C51-C50)/C50 -> 0.0040728738 | E51: 173.8 | F51: 210.7 | G51: 194.5 | H51: 174.6 | I51: 187.2 | J51: 158.3 | K51: 153.9 | L51: 170.9 | M51: 121.1 | N51: 208.4 | O51: 171.4 | P51: 191.2 | Q51: 176.7
A52: 2023 | B52: February | C52: =SUM(E52:Q52) -> 2279.1 | D52: =(C52-C51)/C51 -> -0.0059318707 | E52: 174.4 | F52: 207.7 | G52: 175.2 | H52: 177.3 | I52: 179.3 | J52: 169.5 | K52: 152.7 | L52: 171 | M52: 120 | N52: 209.7 | O52: 172.3 | P52: 193 | Q52: 177
A53: 2023 | B53: March | C53: =SUM(E53:Q53) -> 2279.2 | D53: =(C53-C52)/C52 -> 4.3876969e-05 | E53: 174.4 | F53: 207.7 | G53: 175.2 | H53: 177.3 | I53: 179.2 | J53: 169.5 | K53: 152.8 | L53: 171.1 | M53: 120 | N53: 209.7 | O53: 172.3 | P53: 193 | Q53: 177
A54: 2023 | B54: April | C54: =SUM(E54:Q54) -> 2289.6 | D54: =(C54-C53)/C53 -> 0.0045630046 | E54: 173.8 | F54: 209.3 | G54: 169.6 | H54: 178.4 | I54: 174.9 | J54: 176.3 | K54: 155.4 | L54: 173.4 | M54: 121.3 | N54: 212.9 | O54: 172.9 | P54: 193.5 | Q54: 177.9
A55: 2023 | B55: May | C55: =SUM(E55:Q55) -> 2306.9 | D55: =(C55-C54)/C54 -> 0.007555905 | E55: 173.7 | F55: 214.3 | G55: 173.2 | H55: 179.5 | I55: 170 | J55: 172.2 | K55: 161 | L55: 175.6 | M55: 122.7 | N55: 218 | O55: 173.4 | P55: 194.2 | Q55: 179.1
A57: Identify the absolute changes in inflation over the same 12 months period and identify the biggest individual category contributor (only within broader food category) towards inflation
A58: Food | C58: For 12 months period May 2022-23
A59: Inflation (Food) | C59: Rural | D59: Rural MoM% | E59: Urban | F59: Urban MoM% | G59: Rural+Urban | H59: Rural+Urban MoM%
A60: Cereals and products | C60: =SUMIF(A60:A72,A60,'Raw Data'!D335:D371) -> 152.9 | E60: =SUMIF('PS3'!A60:A72,'PS3'!A60,'Raw Data'!D336:D372) -> 156.7 | G60: =SUMIF(A60:A72,A60,'Raw Data'!D337:D373) -> 154.1
A61: Meat and fish | C61: =SUMIF(A60:A72,A61,'Raw Data'!E335:E371) -> 221.2 | D61: =(C61-C60)/C60 -> 0.44669719 | E61: =SUMIF(A60:A72,A61,'Raw Data'!E336:E372) -> 217 | F61: =(E61-E60)/E60 -> 0.38481174 | G61: =SUMIF(A60:A72,A61,'Raw Data'!E337:E373) -> 217.2 | H61: =(G61-G60)/G60 -> 0.40947437
A62: Egg | C62: =SUMIF(A60:A72,A62,'Raw Data'!F335:F371) -> 162.4 | D62: =(C62-C61)/C61 -> -0.26582278 | E62: =SUMIF(A60:A72,A62,'Raw Data'!F336:F372) -> 169.6 | F62: =(E62-E61)/E61 -> -0.21843318 | G62: =SUMIF(A60:A72,A62,'Raw Data'!F337:F373) -> 172.8 | H62: =(G62-G61)/G61 -> -0.20441989
A63: Milk and products | C63: =SUMIF(A60:A72,A63,'Raw Data'!G335:G371) -> 165.4 | D63: =(C63-C62)/C62 -> 0.018472906 | E63: =SUMIF(A60:A72,A63,'Raw Data'!G336:G372) -> 166.4 | F63: =(E63-E62)/E62 -> -0.018867925 | G63: =SUMIF(A60:A72,A63,'Raw Data'!G337:G373) -> 165.8 | H63: =(G63-G62)/G62 -> -0.040509259
A64: Oils and fats | C64: =SUMIF(A60:A72,A64,'Raw Data'!H335:H371) -> 188.6 | D64: =(C64-C63)/C63 -> 0.14026602 | E64: =SUMIF(A60:A72,A64,'Raw Data'!H336:H372) -> 200.9 | F64: =(E64-E63)/E63 -> 0.20733173 | G64: =SUMIF(A60:A72,A64,'Raw Data'!H337:H373) -> 202.2 | H64: =(G64-G63)/G63 -> 0.21954162
A65: Fruits | C65: =SUMIF(A60:A72,A65,'Raw Data'!I335:I371) -> 169.7 | D65: =(C65-C64)/C64 -> -0.10021209 | E65: =SUMIF(A60:A72,A65,'Raw Data'!I336:I372) -> 169.6 | F65: =(E65-E64)/E64 -> -0.1557989 | G65: =SUMIF(A60:A72,A65,'Raw Data'!I337:I373) -> 179.5 | H65: =(G65-G64)/G64 -> -0.11226508
A66: Vegetables | C66: =SUMIF(A60:A72,A66,'Raw Data'!J335:J371) -> 168.6 | D66: =(C66-C65)/C65 -> -0.0064820271 | E66: =SUMIF(A60:A72,A66,'Raw Data'!J336:J372) -> 208.5 | F66: =(E66-E65)/E65 -> 0.22936321 | G66: =SUMIF(A60:A72,A66,'Raw Data'!J337:J373) -> 182.1 | H66: =(G66-G65)/G65 -> 0.01448468
A67: Pulses and products | C67: =SUMIF(A60:A72,A67,'Raw Data'!K335:K371) -> 164 | D67: =(C67-C66)/C66 -> -0.027283511 | E67: =SUMIF(A60:A72,A67,'Raw Data'!K336:K372) -> 164.3 | F67: =(E67-E66)/E66 -> -0.21199041 | G67: =SUMIF(A60:A72,A67,'Raw Data'!K337:K373) -> 167.1 | H67: =(G67-G66)/G66 -> -0.082372323
A68: Sugar and Confectionery | C68: =SUMIF(A60:A72,A68,'Raw Data'!L335:L371) -> 120 | D68: =(C68-C67)/C67 -> -0.26829268 | E68: =SUMIF(A60:A72,A68,'Raw Data'!L336:L372) -> 120.2 | F68: =(E68-E67)/E67 -> -0.26841144 | G68: =SUMIF(A60:A72,A69,'Raw Data'!L337:L373) -> 120.9 | H68: =(G68-G67)/G67 -> -0.27648115
A69: Spices | C69: =SUMIF(A60:A72,A69,'Raw Data'!M335:M371) -> 195.6 | D69: =(C69-C68)/C68 -> 0.63 | E69: =SUMIF(A60:A72,A69,'Raw Data'!M336:M372) -> 189.7 | F69: =(E69-E68)/E68 -> 0.578203 | G69: =SUMIF(A60:A72,A69,'Raw Data'!M337:M373) -> 193.6 | H69: =(G69-G68)/G68 -> 0.60132341
A70: Non-alcoholic beverages | C70: =SUMIF(A60:A72,A70,'Raw Data'!N335:N371) -> 160.5 | D70: =(C70-C69)/C69 -> -0.17944785 | E70: =SUMIF(A60:A72,A70,'Raw Data'!N336:N372) -> 168.8 | F70: =(E70-E69)/E69 -> -0.11017396 | G70: =SUMIF(A60:A72,A70,'Raw Data'!N337:N373) -> 175.4 | H70: =(G70-G69)/G69 -> -0.094008264
A71: Prepared meals, snacks, sweets etc. | C71: =SUMIF(A60:A72,A71,'Raw Data'!O335:O371) -> 186.3 | D71: =(C71-C70)/C70 -> 0.16074766 | E71: =SUMIF(A60:A72,A71,'Raw Data'!O336:O372) -> 184.8 | F71: =(E71-E70)/E70 -> 0.09478673 | G71: =SUMIF(A60:A72,A71,'Raw Data'!O337:O373) -> 190.4 | H71: =(G71-G70)/G70 -> 0.085518814
A72: Food and beverages | C72: =SUMIF(A60:A72,A72,'Raw Data'!P335:P371) -> 175.5 | D72: =(C72-C71)/C71 -> -0.057971014 | E72: =SUMIF(A60:A72,A72,'Raw Data'!P336:P372) -> 181.8 | F72: =(E72-E71)/E71 -> -0.016233766 | G72: =SUMIF(A60:A72,A72,'Raw Data'!P337:P373) -> 177.8 | H72: =(G72-G71)/G71 -> -0.066176471

Sheet PS4
A1: 4. Investigate how the onset and progression of the COVID-19 pandemic affected inflation rates in India. Analyze the Impact of key pandemic milestone ( first lockdown) on the CPI inflation %, specially focus on categories like healthcare, food, and essential services
A2: We are doing it for Healthcare, Food, and Essential services for Rural, Urban and Rural+Urban.
A4: Rural ( Sector)
E5: Covid
C6: Before Covid | E6: Jan-Dec | F6: After Covid
A7: Sector | B7: Category | C7: 2018-19 | D7: 2019-20 | E7: 2020-21 | F7: 2021-22 | G7: 2022-23 | N7: Sector | O7: Year | P7: Month | Q7: Food | R7: Cereals and products | S7: Meat and fish | T7: Egg | U7: Milk and products | V7: Oils and fats | W7: Fruits | X7: Vegetables | Y7: Pulses and products | Z7: Sugar and Confectionery | AA7: Spices | AB7: Non-alcoholic beverages | AC7: Prepared meals, snacks, sweets etc. | AD7: Food and beverages | AE7: Pan, tobacco and intoxicants | AF7: Clothing | AG7: Footwear | AH7: Clothing and footwear | AI7: Housing | AJ7: Fuel and light | AK7: Household goods and services | AL7: Health | AM7: Transport and communication | AN7: Recreation and amusement | AO7: Education | AP7: Personal care and effects | AQ7: Essential services | AR7: Miscellaneous | AS7: General index
A8: Rural | B8: Food | C8: =('PS4'!Q9-'PS4'!Q8)/'PS4'!Q8 -> -0.015327373 | D8: =('PS4'!Q11-'PS4'!Q10)/'PS4'!Q10 -> 0.10309161 | E8: =('PS4'!Q13-'PS4'!Q12)/'PS4'!Q12 -> 0.083513876 | F8: =('PS4'!Q15-'PS4'!Q14)/'PS4'!Q14 -> 0.049619984 | G8: =('PS4'!Q17-'PS4'!Q16)/'PS4'!Q16 -> 0.057640502 | N8: Rural | O8: 2018 | P8: January | Q8: =SUM(R8:AD8) -> 1800.7 | R8: 136.6 | S8: 144.4 | T8: 143.8 | U8: 142 | V8: 123.2 | W8: 147.9 | X8: 152.1 | Y8: 131.8 | Z8: 119.5 | AA8: 136 | AB8: 131.2 | AC8: 151.8 | AD8: 140.4 | AE8: 153.6 | AF8: 148.3 | AG8: 142.3 | AH8: 147.5 | AI8: NA | AJ8: 142.3 | AK8: 139.8 | AL8: 136 | AM8: 122.7 | AN8: 134.3 | AO8: 141.6 | AP8: 128.6 | AQ8: =AF8+AG8+AK8+AM8+AN8+AO8+AP8+AR8 -> 1089.9 | AR8: 132.3 | AS8: 139.3
A9: Rural | B9: HealthCare | C9: =('PS4'!AL9-'PS4'!AL8)/'PS4'!AL8 -> 0.1 | D9: =('PS4'!AL11-'PS4'!AL10)/'PS4'!AL10 -> 0.034759358 | E9: =('PS4'!AL13-'PS4'!AL12)/'PS4'!AL12 -> 0.037893385 | F9: =('PS4'!AL15-'PS4'!AL14)/'PS4'!AL14 -> 0.070769231 | G9: =('PS4'!AL17-'PS4'!AL16)/'PS4'!AL16 -> 0.050372066 | N9: Rural | O9: 2018 | P9: December | Q9: =SUM(R9:AD9) -> 1773.1 | R9: 137.1 | S9: 151.9 | T9: 137.4 | U9: 142.4 | V9: 124.2 | W9: 140.2 | X9: 136.6 | Y9: 120.9 | Z9: 109.9 | AA9: 140.2 | AB9: 137.8 | AC9: 156 | AD9: 138.5 | AE9: 162.4 | AF9: 151.6 | AG9: 145.9 | AH9: 150.8 | AI9: NA | AJ9: 149 | AK9: 149.5 | AL9: 149.6 | AM9: 128.9 | AN9: 143.3 | AO9: 155.1 | AP9: 133.2 | AQ9: =AF9+AG9+AK9+AM9+AN9+AO9+AP9+AR9 -> 1149.1 | AR9: 141.6 | AS9: 141.9
A10: Rural | B10: Essential Services | C10: =('PS4'!AQ9-'PS4'!AQ8)/'PS4'!AQ8 -> 0.05431691 | D10: =('PS4'!AQ11-'PS4'!AQ10)/'PS4'!AQ10 -> 0.031976997 | E10: =('PS4'!AQ13-'PS4'!AQ12)/'PS4'!AQ12 -> 0.038971947 | F10: =('PS4'!AQ15-'PS4'!AQ14)/'PS4'!AQ14 -> 0.067713366 | G10: =('PS4'!AQ17-'PS4'!AQ16)/'PS4'!AQ16 -> 0.06385054 | N10: Rural | O10: 2019 | P10: January | Q10: =SUM(R10:AD10) -> 1759.6 | R10: 136.6 | S10: 152.5 | T10: 138.2 | U10: 142.4 | V10: 123.9 | W10: 135.5 | X10: 131.7 | Y10: 121.3 | Z10: 108.4 | AA10: 138.9 | AB10: 137 | AC10: 155.8 | AD10: 137.4 | AE10: 162.7 | AF10: 150.6 | AG10: 145.1 | AH10: 149.9 | AI10: NA | AJ10: 146.2 | AK10: 150.1 | AL10: 149.6 | AM10: 128.6 | AN10: 142.9 | AO10: 155.2 | AP10: 133.5 | AQ10: =AF10+AG10+AK10+AM10+AN10+AO10+AP10+AR10 -> 1147.7 | AR10: 141.7 | AS10: 141
N11: Rural | O11: 2019 | P11: December | Q11: =SUM(R11:AD11) -> 1941 | R11: 142.8 | S11: 165.3 | T11: 149.5 | U11: 148.7 | V11: 127.5 | W11: 144.3 | X11: 209.5 | Y11: 138.8 | Z11: 113.6 | AA11: 149.1 | AB11: 139.3 | AC11: 158.3 | AD11: 154.3 | AE11: 167.8 | AF11: 152.6 | AG11: 147.3 | AH11: 151.9 | AI11: NA | AJ11: 149.9 | AK11: 151.2 | AL11: 154.8 | AM11: 135 | AN11: 149.5 | AO11: 161.1 | AP11: 140.6 | AQ11: =AF11+AG11+AK11+AM11+AN11+AO11+AP11+AR11 -> 1184.4 | AR11: 147.1 | AS11: 152.3
A12: Urban (Sector) | N12: Rural | O12: 2020 | P12: January | Q12: =SUM(R12:AD12) -> 1938.6 | R12: 143.7 | S12: 167.3 | T12: 153.5 | U12: 150.5 | V12: 132 | W12: 142.2 | X12: 191.5 | Y12: 141.1 | Z12: 113.8 | AA12: 151.6 | AB12: 139.7 | AC12: 158.7 | AD12: 153 | AE12: 168.6 | AF12: 152.8 | AG12: 147.4 | AH12: 152.1 | AI12: NA | AJ12: 150.4 | AK12: 151.7 | AL12: 155.7 | AM12: 136.3 | AN12: 150.1 | AO12: 161.7 | AP12: 142.5 | AQ12: =AF12+AG12+AK12+AM12+AN12+AO12+AP12+AR12 -> 1190.6 | AR12: 148.1 | AS12: 151.9
E13: Covid | N13: Rural | O13: 2020 | P13: December | Q13: =SUM(R13:AD13) -> 2100.5 | R13: 144.6 | S13: 188.5 | T13: 173.4 | U13: 154 | V13: 150 | W13: 145.9 | X13: 225.2 | Y13: 159.5 | Z13: 114.4 | AA13: 163.5 | AB13: 153.4 | AC13: 163.6 | AD13: 164.5 | AE13: 183.6 | AF13: 157 | AG13: 151.6 | AH13: 156.3 | AI13: NA | AJ13: 148.7 | AK13: 153.4 | AL13: 161.6 | AM13: 146.4 | AN13: 153.9 | AO13: 162.9 | AP13: 156.6 | AQ13: =AF13+AG13+AK13+AM13+AN13+AO13+AP13+AR13 -> 1237 | AR13: 155.2 | AS13: 160.7
C14: Before Covid | E14: Jan-Dec | F14: After Covid | N14: Rural | O14: 2021 | P14: January | Q14: =SUM(R14:AD14) -> 2065.7 | R14: 143.4 | S14: 187.5 | T14: 173.4 | U14: 154 | V14: 154.8 | W14: 147 | X14: 187.8 | Y14: 159.5 | Z14: 113.8 | AA14: 164.5 | AB14: 156.1 | AC14: 164.3 | AD14: 159.6 | AE14: 184.6 | AF14: 157.5 | AG14: 152.4 | AH14: 156.8 | AI14: NA | AJ14: 150.9 | AK14: 153.9 | AL14: 162.5 | AM14: 147.5 | AN14: 155.1 | AO14: 163.5 | AP14: 156.2 | AQ14: =AF14+AG14+AK14+AM14+AN14+AO14+AP14+AR14 -> 1242 | AR14: 155.9 | AS14: 158.5
A15: Sector | B15: Category | C15: 2018-19 | D15: 2019-20 | E15: 2020-21 | F15: 2021-22 | G15: 2022-23 | N15: Rural | O15: 2021 | P15: December | Q15: =SUM(R15:AD15) -> 2168.2 | R15: 147.4 | S15: 197 | T15: 176.5 | U15: 159.8 | V15: 195.8 | W15: 152 | X15: 172.3 | Y15: 164.5 | Z15: 120.6 | AA15: 171.7 | AB15: 169.7 | AC15: 175.1 | AD15: 165.8 | AE15: 190.8 | AF15: 171.8 | AG15: 167.3 | AH15: 171.2 | AI15: NA | AJ15: 165.6 | AK15: 163.9 | AL15: 174 | AM15: 160.1 | AN15: 164.5 | AO15: 169.7 | AP15: 162.8 | AQ15: =AF15+AG15+AK15+AM15+AN15+AO15+AP15+AR15 -> 1326.1 | AR15: 166 | AS15: 167
A16: Urban | B16: Food | C16: =(Q22-Q21)/Q21 -> -0.00097237316 | D16: =(Q24-Q23)/Q23 -> 0.12176804 | E16: =(Q26-Q25)/Q25 -> 0.092525959 | F16: =(Q28-Q27)/Q27 -> 0.052122079 | G16: =(Q30-Q29)/Q29 -> 0.049892532 | N16: Rural | O16: 2022 | P16: January | Q16: =SUM(R16:AD16) -> 2153 | R16: 148.3 | S16: 196.9 | T16: 178 | U16: 160.5 | V16: 192.6 | W16: 151.2 | X16: 159.2 | Y16: 164 | Z16: 119.3 | AA16: 173.3 | AB16: 169.8 | AC16: 175.8 | AD16: 164.1 | AE16: 190.7 | AF16: 173.2 | AG16: 169.3 | AH16: 172.7 | AI16: NA | AJ16: 165.8 | AK16: 164.9 | AL16: 174.7 | AM16: 160.8 | AN16: 164.9 | AO16: 169.9 | AP16: 163.2 | AQ16: =AF16+AG16+AK16+AM16+AN16+AO16+AP16+AR16 -> 1332.8 | AR16: 166.6 | AS16: 166.4
A17: Urban | B17: HealthCare | C17: =(AL22-AL21)/AL21 -> 0.064341085 | D17: =(AL24-AL23)/AL23 -> 0.039187228 | E17: =(AL26-AL25)/AL25 -> 0.063282337 | F17: =(AL28-AL27)/AL27 -> 0.071382219 | G17: =(AL30-AL29)/AL29 -> 0.066827213 | N17: Rural | O17: 2022 | P17: December | Q17: =SUM(R17:AD17) -> 2277.1 | R17: 168.8 | S17: 206.9 | T17: 189.1 | U17: 173.4 | V17: 193.9 | W17: 156.7 | X17: 150.2 | Y17: 170.5 | Z17: 121.2 | AA17: 207.5 | AB17: 176.8 | AC17: 187.7 | AD17: 174.4 | AE17: 195.9 | AF17: 188.1 | AG17: 185.9 | AH17: 187.8 | AI17: NA | AJ17: 182.8 | AK17: 176.4 | AL17: 183.5 | AM17: 167.8 | AN17: 171.2 | AO17: 177.3 | AP17: 175.7 | AQ17: =AF17+AG17+AK17+AM17+AN17+AO17+AP17+AR17 -> 1417.9 | AR17: 175.5 | AS17: 177.1
A18: Urban | B18: Essential Services | C18: =(AQ22-AQ21)/AQ21 -> 0.045387851 | D18: =(AQ24-AQ23)/AQ23 -> 0.038213585 | E18: =(AQ26-AQ25)/AQ25 -> 0.053216269 | F18: =(AQ28-AQ27)/AQ27 -> 0.065298507 | G18: =(AQ30-AQ29)/AQ29 -> 0.07004353 | N18: Rural | O18: 2023 | P18: January | Q18: =SUM(R18:AD18) -> 2283.2 | R18: 174 | S18: 208.3 | T18: 192.9 | U18: 174.3 | V18: 192.6 | W18: 156.3 | X18: 142.9 | Y18: 170.7 | Z18: 120.3 | AA18: 210.5 | AB18: 176.9 | AC18: 188.5 | AD18: 175 | AE18: 196.9 | AF18: 189 | AG18: 186.3 | AH18: 188.6 | AI18: NA | AJ18: 183.2 | AK18: 177.2 | AL18: 184.7 | AM18: 168.2 | AN18: 171.8 | AO18: 177.8 | AP18: 178.4 | AQ18: =AF18+AG18+AK18+AM18+AN18+AO18+AP18+AR18 -> 1425.2 | AR18: 176.5 | AS18: 177.8
A20: Rural+Urban (Sector) | N20: Sector | O20: Year | P20: Month | Q20: Food | R20: Cereals and products | S20: Meat and fish | T20: Egg | U20: Milk and products | V20: Oils and fats | W20: Fruits | X20: Vegetables | Y20: Pulses and products | Z20: Sugar and Confectionery | AA20: Spices | AB20: Non-alcoholic beverages | AC20: Prepared meals, snacks, sweets etc. | AD20: Food and beverages | AE20: Pan, tobacco and intoxicants | AF20: Clothing | AG20: Footwear | AH20: Clothing and footwear | AI20: Housing | AJ20: Fuel and light | AK20: Household goods and services | AL20: Health | AM20: Transport and communication | AN20: Recreation and amusement | AO20: Education | AP20: Personal care and effects | AQ20: Essential Services | AR20: Miscellaneous | AS20: General index
E21: Covid | N21: Urban | O21: 2018 | P21: January | Q21: =SUM(R21:AD21) -> 1748.3 | R21: 134.6 | S21: 143.7 | T21: 143.6 | U21: 139.6 | V21: 116.4 | W21: 133.8 | X21: 150.5 | Y21: 118.4 | Z21: 117.3 | AA21: 140.5 | AB21: 125.9 | AC21: 146.8 | AD21: 137.2 | AE21: 157.7 | AF21: 136 | AG21: 125.9 | AH21: 134.4 | AI21: 140.4 | AJ21: 127.3 | AK21: 129.5 | AL21: 129 | AM21: 116.3 | AN21: 126.2 | AO21: 137.1 | AP21: 125.5 | AQ21: =AF21+AG21+AK21+AM21+AN21+AO21+AP21+AR21 -> 1022.3 | AR21: 125.8 | AS21: 134.1
C22: Before Covid | E22: Jan-Dec | F22: After Covid | N22: Urban | O22: 2018 | P22: December | Q22: =SUM(R22:AD22) -> 1746.6 | R22: 138.5 | S22: 147.8 | T22: 141.1 | U22: 141.6 | V22: 118.1 | W22: 138.5 | X22: 132.4 | Y22: 117.5 | Z22: 111 | AA22: 141.5 | AB22: 128.1 | AC22: 152.9 | AD22: 137.6 | AE22: 164.6 | AF22: 142.7 | AG22: 130.3 | AH22: 140.8 | AI22: 146.5 | AJ22: 132.4 | AK22: 136.2 | AL22: 137.3 | AM22: 118.8 | AN22: 131.7 | AO22: 146.5 | AP22: 130.8 | AQ22: =AF22+AG22+AK22+AM22+AN22+AO22+AP22+AR22 -> 1068.7 | AR22: 131.7 | AS22: 138
A23: Sector | B23: Category | C23: 2018-19 | D23: 2019-20 | E23: 2020-21 | F23: 2021-22 | G23: 2022-23 | N23: Urban | O23: 2019 | P23: January | Q23: =SUM(R23:AD23) -> 1744.3 | R23: 138.3 | S23: 149.4 | T23: 143.5 | U23: 141.7 | V23: 118.1 | W23: 135.2 | X23: 130.5 | Y23: 118.2 | Z23: 110.4 | AA23: 140.4 | AB23: 128.1 | AC23: 153.2 | AD23: 137.3 | AE23: 164.7 | AF23: 143 | AG23: 130.4 | AH23: 141.1 | AI23: 147.7 | AJ23: 128.6 | AK23: 136.3 | AL23: 137.8 | AM23: 118.6 | AN23: 131.9 | AO23: 146.6 | AP23: 131.7 | AQ23: =AF23+AG23+AK23+AM23+AN23+AO23+AP23+AR23 -> 1070.3 | AR23: 131.8 | AS23: 138
A24: Rural+Urban | B24: Food | C24: =(Q35-Q34)/Q34 -> -0.0096072813 | D24: =(Q37-Q36)/Q36 -> 0.10990076 | E24: =(Q39-Q38)/Q38 -> 0.086940837 | F24: =(Q41-Q40)/Q40 -> 0.050276908 | G24: =(Q43-Q42)/Q42 -> 0.055078089 | N24: Urban | O24: 2019 | P24: December | Q24: =SUM(R24:AD24) -> 1956.7 | R24: 144.9 | S24: 164.5 | T24: 153.7 | U24: 147.5 | V24: 122.7 | W24: 147.2 | X24: 231.5 | Y24: 137.2 | Z24: 114.7 | AA24: 148 | AB24: 130.8 | AC24: 157.7 | AD24: 156.3 | AE24: 170.4 | AF24: 146.8 | AG24: 132.8 | AH24: 144.6 | AI24: 152.8 | AJ24: 133.6 | AK24: 139.8 | AL24: 143.2 | AM24: 125.2 | AN24: 136.8 | AO24: 151.9 | AP24: 140.2 | AQ24: =AF24+AG24+AK24+AM24+AN24+AO24+AP24+AR24 -> 1111.2 | AR24: 137.7 | AS24: 148.3
A25: Rural+Urban | B25: HealthCare | C25: =(AL35-AL34)/AL34 -> 0.087021755 | D25: =(AL37-AL36)/AL36 -> 0.036526533 | E25: =(AL39-AL38)/AL38 -> 0.046957672 | F25: =(AL41-AL40)/AL40 -> 0.070935342 | G25: =(AL43-AL42)/AL42 -> 0.056592765 | N25: Urban | O25: 2020 | P25: January | Q25: =SUM(R25:AD25) -> 1945.4 | R25: 145.6 | S25: 167.6 | T25: 157 | U25: 149.3 | V25: 126.3 | W25: 144.4 | X25: 207.8 | Y25: 139.1 | Z25: 114.8 | AA25: 149.5 | AB25: 131.1 | AC25: 158.5 | AD25: 154.4 | AE25: 170.8 | AF25: 147 | AG25: 133.2 | AH25: 144.9 | AI25: 153.9 | AJ25: 135.1 | AK25: 140.1 | AL25: 143.8 | AM25: 126.1 | AN25: 137.2 | AO25: 152.1 | AP25: 142.1 | AQ25: =AF25+AG25+AK25+AM25+AN25+AO25+AP25+AR25 -> 1116.2 | AR25: 138.4 | AS25: 148.2
A26: Rural+Urban | B26: Essential Services | C26: =(AQ35-AQ34)/AQ34 -> 0.049040915 | D26: =(AQ37-AQ36)/AQ36 -> 0.03423115 | E26: =(AQ39-AQ38)/AQ38 -> 0.046199185 | F26: =(AQ41-AQ40)/AQ40 -> 0.067464905 | G26: =(AQ43-AQ42)/AQ42 -> 0.067318049 | N26: Urban | O26: 2020 | P26: December | Q26: =SUM(R26:AD26) -> 2125.4 | R26: 149 | S26: 195.7 | T26: 178.3 | U26: 154.2 | V26: 140.7 | W26: 149.7 | X26: 240.9 | Y26: 161.5 | Z26: 117.1 | AA26: 161.9 | AB26: 143.3 | AC26: 166.1 | AD26: 167 | AE26: 190.2 | AF26: 151.9 | AG26: 136.7 | AH26: 149.6 | AI26: 158.4 | AJ26: 137.9 | AK26: 145.5 | AL26: 152.9 | AM26: 135.5 | AN26: 144.3 | AO26: 156.9 | AP26: 157.9 | AQ26: =AF26+AG26+AK26+AM26+AN26+AO26+AP26+AR26 -> 1175.6 | AR26: 146.9 | AS26: 156.9
N27: Urban | O27: 2021 | P27: January | Q27: =SUM(R27:AD27) -> 2097 | R27: 148 | S27: 194.8 | T27: 178.4 | U27: 154.4 | V27: 144.1 | W27: 152.6 | X27: 206.8 | Y27: 162.1 | Z27: 116.3 | AA27: 163 | AB27: 145.9 | AC27: 167.2 | AD27: 163.4 | AE27: 191.8 | AF27: 152.5 | AG27: 137.3 | AH27: 150.2 | AI27: 157.7 | AJ27: 142.9 | AK27: 145.7 | AL27: 154.1 | AM27: 136.9 | AN27: 145.4 | AO27: 156.1 | AP27: 157.7 | AQ27: =AF27+AG27+AK27+AM27+AN27+AO27+AP27+AR27 -> 1179.2 | AR27: 147.6 | AS27: 156
N28: Urban | O28: 2021 | P28: December | Q28: =SUM(R28:AD28) -> 2206.3 | R28: 151.6 | S28: 202.2 | T28: 180 | U28: 160 | V28: 173.5 | W28: 158.3 | X28: 219.5 | Y28: 164.2 | Z28: 121.9 | AA28: 168.2 | AB28: 156.5 | AC28: 178.2 | AD28: 172.2 | AE28: 196.8 | AF28: 163.3 | AG28: 146.7 | AH28: 160.7 | AI28: 163.4 | AJ28: 161.7 | AK28: 156 | AL28: 165.1 | AM28: 151.8 | AN28: 157.6 | AO28: 160.6 | AP28: 162.4 | AQ28: =AF28+AG28+AK28+AM28+AN28+AO28+AP28+AR28 -> 1256.2 | AR28: 157.8 | AS28: 165.2
N29: Urban | O29: 2022 | P29: January | Q29: =SUM(R29:AD29) -> 2186.7 | R29: 152.2 | S29: 202.1 | T29: 180.1 | U29: 160.4 | V29: 171 | W29: 156.5 | X29: 203.6 | Y29: 163.8 | Z29: 121.3 | AA29: 169.8 | AB29: 156.6 | AC29: 179 | AD29: 170.3 | AE29: 196.4 | AF29: 164.7 | AG29: 148.5 | AH29: 162.2 | AI29: 164.5 | AJ29: 161.6 | AK29: 156.8 | AL29: 166.1 | AM29: 152.7 | AN29: 158.4 | AO29: 161 | AP29: 162.8 | AQ29: =AF29+AG29+AK29+AM29+AN29+AO29+AP29+AR29 -> 1263.5 | AR29: 158.6 | AS29: 165
N30: Urban | O30: 2022 | P30: December | Q30: =SUM(R30:AD30) -> 2295.8 | R30: 170.2 | S30: 212.9 | T30: 191.9 | U30: 173.9 | V30: 179.1 | W30: 159.5 | X30: 178.7 | Y30: 171.3 | Z30: 123.1 | AA30: 200.5 | AB30: 162.8 | AC30: 193.3 | AD30: 178.6 | AE30: 201.1 | AF30: 177.7 | AG30: 164.5 | AH30: 175.7 | AI30: 170.7 | AJ30: 180.6 | AK30: 167.3 | AL30: 177.2 | AM30: 159.4 | AN30: 167.1 | AO30: 171.8 | AP30: 176 | AQ30: =AF30+AG30+AK30+AM30+AN30+AO30+AP30+AR30 -> 1352 | AR30: 168.2 | AS30: 174.1
N31: Urban | O31: 2023 | P31: January | Q31: =SUM(R31:AD31) -> 2310.2 | R31: 173.3 | S31: 215.2 | T31: 197 | U31: 175.2 | V31: 178 | W31: 160.5 | X31: 175.3 | Y31: 171.2 | Z31: 122.7 | AA31: 204.3 | AB31: 163.7 | AC31: 194.3 | AD31: 179.5 | AE31: 201.6 | AF31: 178.7 | AG31: 165.3 | AH31: 176.6 | AI31: 172.1 | AJ31: 180.1 | AK31: 168 | AL31: 178.5 | AM31: 159.5 | AN31: 167.8 | AO31: 171.8 | AP31: 178.8 | AQ31: =AF31+AG31+AK31+AM31+AN31+AO31+AP31+AR31 -> 1358.8 | AR31: 168.9 | AS31: 174.9
N33: Sector | O33: Year | P33: Month | Q33: Food | R33: Cereals and products | S33: Meat and fish | T33: Egg | U33: Milk and products | V33: Oils and fats | W33: Fruits | X33: Vegetables | Y33: Pulses and products | Z33: Sugar and Confectionery | AA33: Spices | AB33: Non-alcoholic beverages | AC33: Prepared meals, snacks, sweets etc. | AD33: Food and beverages | AE33: Pan, tobacco and intoxicants | AF33: Clothing | AG33: Footwear | AH33: Clothing and footwear | AI33: Housing | AJ33: Fuel and light | AK33: Household goods and services | AL33: Health | AM33: Transport and communication | AN33: Recreation and amusement | AO33: Education | AP33: Personal care and effects | AQ33: Essential Services | AR33: Miscellaneous | AS33: General index
N34: Rural+Urban | O34: 2018 | P34: January | Q34: =SUM(R34:AD34) -> 1779.9 | R34: 136 | S34: 144.2 | T34: 143.7 | U34: 141.1 | V34: 120.7 | W34: 141.3 | X34: 151.6 | Y34: 127.3 | Z34: 118.8 | AA34: 137.5 | AB34: 129 | AC34: 149.5 | AD34: 139.2 | AE34: 154.7 | AF34: 143.5 | AG34: 135.5 | AH34: 142.3 | AI34: 140.4 | AJ34: 136.6 | AK34: 134.9 | AL34: 133.3 | AM34: 119.3 | AN34: 129.7 | AO34: 139 | AP34: 127.3 | AQ34: =AF34+AG34+AK34+AM34+AN34+AO34+AP34+AR34 -> 1058.3 | AR34: 129.1 | AS34: 136.9
N35: Rural+Urban | O35: 2018 | P35: December | Q35: =SUM(R35:AD35) -> 1762.8 | R35: 137.5 | S35: 150.5 | T35: 138.8 | U35: 142.1 | V35: 122 | W35: 139.4 | X35: 135.2 | Y35: 119.8 | Z35: 110.3 | AA35: 140.6 | AB35: 133.8 | AC35: 154.6 | AD35: 138.2 | AE35: 163 | AF35: 148.1 | AG35: 139.4 | AH35: 146.8 | AI35: 146.5 | AJ35: 142.7 | AK35: 143.2 | AL35: 144.9 | AM35: 123.6 | AN35: 136.8 | AO35: 150.1 | AP35: 132.2 | AQ35: =AF35+AG35+AK35+AM35+AN35+AO35+AP35+AR35 -> 1110.2 | AR35: 136.8 | AS35: 140.1
N36: Rural+Urban | O36: 2019 | P36: January | Q36: =SUM(R36:AD36) -> 1753.4 | R36: 137.1 | S36: 151.4 | T36: 140.2 | U36: 142.1 | V36: 121.8 | W36: 135.4 | X36: 131.3 | Y36: 120.3 | Z36: 109.1 | AA36: 139.4 | AB36: 133.3 | AC36: 154.6 | AD36: 137.4 | AE36: 163.2 | AF36: 147.6 | AG36: 139 | AH36: 146.4 | AI36: 147.7 | AJ36: 139.5 | AK36: 143.6 | AL36: 145.1 | AM36: 123.3 | AN36: 136.7 | AO36: 150.2 | AP36: 132.8 | AQ36: =AF36+AG36+AK36+AM36+AN36+AO36+AP36+AR36 -> 1110.1 | AR36: 136.9 | AS36: 139.6
N37: Rural+Urban | O37: 2019 | P37: December | Q37: =SUM(R37:AD37) -> 1946.1 | R37: 143.5 | S37: 165 | T37: 151.1 | U37: 148.3 | V37: 125.7 | W37: 145.7 | X37: 217 | Y37: 138.3 | Z37: 114 | AA37: 148.7 | AB37: 135.8 | AC37: 158 | AD37: 155 | AE37: 168.5 | AF37: 150.3 | AG37: 141.3 | AH37: 149 | AI37: 152.8 | AJ37: 143.7 | AK37: 145.8 | AL37: 150.4 | AM37: 129.8 | AN37: 142.3 | AO37: 155.7 | AP37: 140.4 | AQ37: =AF37+AG37+AK37+AM37+AN37+AO37+AP37+AR37 -> 1148.1 | AR37: 142.5 | AS37: 150.4
N38: Rural+Urban | O38: 2020 | P38: January | Q38: =SUM(R38:AD38) -> 1940.4 | R38: 144.3 | S38: 167.4 | T38: 154.9 | U38: 150.1 | V38: 129.9 | W38: 143.2 | X38: 197 | Y38: 140.4 | Z38: 114.1 | AA38: 150.9 | AB38: 136.1 | AC38: 158.6 | AD38: 153.5 | AE38: 169.2 | AF38: 150.5 | AG38: 141.5 | AH38: 149.2 | AI38: 153.9 | AJ38: 144.6 | AK38: 146.2 | AL38: 151.2 | AM38: 130.9 | AN38: 142.8 | AO38: 156.1 | AP38: 142.3 | AQ38: =AF38+AG38+AK38+AM38+AN38+AO38+AP38+AR38 -> 1153.7 | AR38: 143.4 | AS38: 150.2
N39: Rural+Urban | O39: 2020 | P39: December | Q39: =SUM(R39:AD39) -> 2109.1 | R39: 146 | S39: 191 | T39: 175.3 | U39: 154.1 | V39: 146.6 | W39: 147.7 | X39: 230.5 | Y39: 160.2 | Z39: 115.3 | AA39: 163 | AB39: 149.2 | AC39: 164.8 | AD39: 165.4 | AE39: 185.4 | AF39: 155 | AG39: 145.4 | AH39: 153.6 | AI39: 158.4 | AJ39: 144.6 | AK39: 149.7 | AL39: 158.3 | AM39: 140.7 | AN39: 148.5 | AO39: 159.4 | AP39: 157.1 | AQ39: =AF39+AG39+AK39+AM39+AN39+AO39+AP39+AR39 -> 1207 | AR39: 151.2 | AS39: 158.9
N40: Rural+Urban | O40: 2021 | P40: January | Q40: =SUM(R40:AD40) -> 2076.5 | R40: 144.9 | S40: 190.1 | T40: 175.3 | U40: 154.1 | V40: 150.9 | W40: 149.6 | X40: 194.2 | Y40: 160.4 | Z40: 114.6 | AA40: 164 | AB40: 151.8 | AC40: 165.6 | AD40: 161 | AE40: 186.5 | AF40: 155.5 | AG40: 146.1 | AH40: 154.2 | AI40: 157.7 | AJ40: 147.9 | AK40: 150 | AL40: 159.3 | AM40: 141.9 | AN40: 149.6 | AO40: 159.2 | AP40: 156.8 | AQ40: =AF40+AG40+AK40+AM40+AN40+AO40+AP40+AR40 -> 1211 | AR40: 151.9 | AS40: 157.3
N41: Rural+Urban | O41: 2021 | P41: December | Q41: =SUM(R41:AD41) -> 2180.9 | R41: 148.7 | S41: 198.8 | T41: 177.9 | U41: 159.9 | V41: 187.6 | W41: 154.9 | X41: 188.3 | Y41: 164.4 | Z41: 121 | AA41: 170.5 | AB41: 164.2 | AC41: 176.5 | AD41: 168.2 | AE41: 192.4 | AF41: 168.5 | AG41: 158.7 | AH41: 167 | AI41: 163.4 | AJ41: 164.1 | AK41: 160.2 | AL41: 170.6 | AM41: 155.7 | AN41: 160.6 | AO41: 164.4 | AP41: 162.6 | AQ41: =AF41+AG41+AK41+AM41+AN41+AO41+AP41+AR41 -> 1292.7 | AR41: 162 | AS41: 166.2
N42: Rural+Urban | O42: 2022 | P42: January | Q42: =SUM(R42:AD42) -> 2164.2 | R42: 149.5 | S42: 198.7 | T42: 178.8 | U42: 160.5 | V42: 184.7 | W42: 153.7 | X42: 174.3 | Y42: 163.9 | Z42: 120 | AA42: 172.1 | AB42: 164.3 | AC42: 177.3 | AD42: 166.4 | AE42: 192.2 | AF42: 169.9 | AG42: 160.7 | AH42: 168.5 | AI42: 164.5 | AJ42: 164.2 | AK42: 161.1 | AL42: 171.4 | AM42: 156.5 | AN42: 161.2 | AO42: 164.7 | AP42: 163 | AQ42: =AF42+AG42+AK42+AM42+AN42+AO42+AP42+AR42 -> 1299.8 | AR42: 162.7 | AS42: 165.7
N43: Rural+Urban | O43: 2022 | P43: December | Q43: =SUM(R43:AD43) -> 2283.4 | R43: 169.2 | S43: 209 | T43: 190.2 | U43: 173.6 | V43: 188.5 | W43: 158 | X43: 159.9 | Y43: 170.8 | Z43: 121.8 | AA43: 205.2 | AB43: 171 | AC43: 190.3 | AD43: 175.9 | AE43: 197.3 | AF43: 184 | AG43: 177 | AH43: 183 | AI43: 170.7 | AJ43: 182 | AK43: 172.1 | AL43: 181.1 | AM43: 163.4 | AN43: 168.9 | AO43: 174.1 | AP43: 175.8 | AQ43: =AF43+AG43+AK43+AM43+AN43+AO43+AP43+AR43 -> 1387.3 | AR43: 172 | AS43: 175.7
N44: Rural+Urban | O44: 2023 | P44: January | Q44: =SUM(R44:AD44) -> 2292.7 | R44: 173.8 | S44: 210.7 | T44: 194.5 | U44: 174.6 | V44: 187.2 | W44: 158.3 | X44: 153.9 | Y44: 170.9 | Z44: 121.1 | AA44: 208.4 | AB44: 171.4 | AC44: 191.2 | AD44: 176.7 | AE44: 198.2 | AF44: 184.9 | AG44: 177.6 | AH44: 183.8 | AI44: 172.1 | AJ44: 182 | AK44: 172.9 | AL44: 182.3 | AM44: 163.6 | AN44: 169.5 | AO44: 174.3 | AP44: 178.6 | AQ44: =AF44+AG44+AK44+AM44+AN44+AO44+AP44+AR44 -> 1394.2 | AR44: 172.8 | AS44: 176.5

Sheet PS5
A1: 5. Investigate how major global economic events (like imported oil price fluctuations) have influenced India's inflation. This can include an analysis of imported goods and their price trends.
A2: a. For the purpose of this analysis, focus only on the imported oil price fluctuations for years 2021 to 2023 (Month-on-month)
A4: OIL Prices taken from (PPAC.GOV) for crude prices.
A5: Year | B5: 33329 | C5: 33359 | D5: 33390 | E5: 33420 | F5: 33451 | G5: 33482 | H5: 33512 | I5: 33543 | J5: 33573 | K5: 33604 | L5: 33635 | M5: 33664 | N5: Average | O5: Ratio *
A6: 2000-01 | B6: 22.51 | C6: 26.6 | D6: 28.49 | E6: 27.26 | F6: 28.328849 | G6: 31.34 | H6: 30.5 | I6: 30.926622 | J6: 23.25 | K6: 24.02 | L6: 25.92 | M6: 23.82 | N6: 26.924167 | O6: 57:43
A7: 2001-02 | B7: 24.82 | C7: 26.95 | D7: 26.63 | E7: 23.99 | F7: 25.01 | G7: 24.79 | H7: 20.05 | I7: 18.24 | J7: 18.24 | K7: 18.92 | L7: 19.529987 | M7: 23.31 | N7: 22.551701 | O7: 57:43
A8: 2002-03 | B8: 25.029406 | C8: 24.994865 | D8: 24.051814 | E8: 25.183222 | F8: 25.855818 | G8: 27.495243 | H8: 26.902101 | I8: 23.682512 | J8: 27.110101 | K8: 29.59255 | L8: 31.308381 | M8: 28.825039 | N8: 26.6 | O8: 57:43
A9: 2003-04 | B9: 24.214592 | C9: 24.988879 | D9: 26.425925 | E9: 27.45845 | F9: 28.663599 | G9: 26.265218 | H9: 28.449944 | I9: 28.226284 | J9: 28.966611 | K9: 29.999534 | L9: 29.647267 | M9: 32.210323 | N9: 27.98 | O9: 57:43
A10: 2004-05 | B10: 32.365205 | C10: 36.078851 | D10: 34.159548 | E10: 36.353382 | F10: 40.5172 | G10: 39.149477 | H10: 43.375467 | I10: 38.89887 | J10: 36.816215 | K10: 40.962002 | L10: 42.670599 | M10: 49.27002 | N10: 39.205833 | O10: 57:43
A11: 2005-06 | B11: 49.427602 | C11: 46.995224 | D11: 52.720745 | E11: 55.008083 | F11: 60.048336 | G11: 59.739214 | H11: 56.279062 | I11: 53.143808 | J11: 55.045629 | K11: 60.542917 | L11: 58.95333 | M11: 60.011574 | N11: 55.72 | O11: 58:42
A12: 2006-07 | B12: 67.055031 | C12: 67.223591 | D12: 66.897535 | E12: 71.285795 | F12: 70.775922 | G12: 60.933454 | H12: 57.270685 | I12: 57.793638 | J12: 60.344671 | K12: 52.529441 | L12: 56.531045 | M12: 60.262108 | N12: 62.46 | O12: 59.8:40.2
A13: 2007-08 | B13: 65.481951 | C13: 65.695437 | D13: 68.099251 | E13: 72.575062 | F13: 68.982337 | G13: 74.776604 | H13: 79.327164 | I13: 89.107014 | J13: 87.921265 | K13: 89.517554 | L13: 92.374237 | M13: 99.759819 | N13: 79.249167 | O13: 61.4:38.6
A14: 2008-09 | B14: 105.72015 | C14: 120.90896 | D14: 129.71536 | E14: 132.47125 | F14: 113.05439 | G14: 96.812892 | H14: 69.121527 | I14: 50.907636 | J14: 40.611433 | K14: 43.986058 | L14: 43.217028 | M14: 46.021762 | N14: 83.566667 | O14: 62.3:37.7
A15: 2009-10 | B15: 50.135602 | C15: 58.00336 | D15: 69.115276 | E15: 64.82461 | F15: 71.979192 | G15: 67.70165 | H15: 73.064289 | I15: 77.390866 | J15: 75.016223 | K15: 76.608826 | L15: 73.694278 | M15: 78.0183 | N15: 69.76227 | O15: 63.5:36.5
A16: 2010-11 | B16: 84.081729 | C16: 76.161428 | D16: 74.33109 | E16: 73.543052 | F16: 75.126989 | G16: 76.093 | H16: 81.109814 | I16: 84.255699 | J16: 89.772982 | K16: 93.868448 | L16: 101.621 | M16: 110.71447 | N16: 85.09 | O16: 67.6:32.4
A17: 2011-12 | B17: 118.63579 | C17: 110.80254 | D17: 109.99407 | E17: 112.52711 | F17: 106.93536 | G17: 108.79065 | H17: 106.10837 | I17: 109.61574 | J17: 107.19389 | K17: 110.46828 | L17: 117.6662 | M17: 123.61056 | N17: 111.89 | O17: 65.2:34.8
... A30: 2024-25 | B30: 89.437476 | C30: 83.624938 | D30: 82.552871 | E30: 84.148165 | F30: 78.270687 | G30: 73.694889 | H30: 75.124705 | I30: 73.016987 | J30: 73.336847 | K30: 80.196197 | L30: 77.328567 | M30: 72.466606 | N30: 78.560027 | O30: 78.50:21.50

Sheet PS5.2
A1: b. Identify trends in oil price change with change in inflation prices of all the categories and identify category whose inflation prices strongly changes with fluctuations in imported oil price.
A2: Rural CPI Inflation | C2: Correlation
C3: =CORREL($B$5:$B$28,C5:C28) -> 0.50454041 | D3: =CORREL($B$5:$B$28,D5:D28) -> 0.8335211 | E3: =CORREL($B$5:$B$28,E5:E28) -> -0.19207236 | F3: =CORREL($B$5:$B$28,F5:F28) -> 0.63400524 | G3: =CORREL($B$5:$B$28,G5:G28) -> 0.82628873 | H3: =CORREL($B$5:$B$28,H5:H28) -> 0.65128163 | I3: =CORREL($B$5:$B$28,I5:I28) -> 0.2706887 | J3: =CORREL($B$5:$B$28,J5:J28) -> 0.4523074 | ... AC3: =CORREL($B$5:$B$28,AC5:AC28) -> 0.73352065
A4: Date | B4: Oil Prices | C4: Cereals and products | D4: Meat and fish | E4: Egg | F4: Milk and products | G4: Oils and fats | H4: Fruits | I4: Vegetables | J4: Pulses and products | K4: Sugar and Confectionery | L4: Spices | M4: Non-alcoholic beverages | N4: Prepared meals, snacks, sweets etc. | O4: Food and beverages | P4: Pan, tobacco and intoxicants | Q4: Clothing | R4: Footwear | S4: Clothing and footwear | T4: Housing | U4: Fuel and light | V4: Household goods and services | W4: Health | X4: Transport and communication | Y4: Recreation and amusement | Z4: Education | AA4: Personal care and effects | AB4: Miscellaneous | AC4: General index
A5: 44197 | B5: 54.79457 | C5: 143.4 | D5: 187.5 | E5: 173.4 | F5: 154 | G5: 154.8 | H5: 147 | I5: 187.8 | J5: 159.5 | K5: 113.8 | L5: 164.5 | M5: 156.1 | N5: 164.3 | O5: 159.6 | P5: 184.6 | Q5: 157.5 | R5: 152.4 | S5: 156.8 | T5: NA | U5: 150.9 | V5: 153.9 | W5: 162.5 | X5: 147.5 | Y5: 155.1 | Z5: 163.5 | AA5: 156.2 | AB5: 155.9 | AC5: 158.5
A6: 44228 | B6: 61.216117 | C6: 142.8 | D6: 184 | E6: 168 | F6: 154.4 | G6: 163 | H6: 147.8 | I6: 149.7 | J6: 158.3 | K6: 111.8 | L6: 165 | M6: 160 | N6: 165.8 | O6: 154.7 | P6: 186.5 | Q6: 159.1 | R6: 153.9 | S6: 158.4 | T6: NA | U6: 154.4 | V6: 154.8 | W6: 164.3 | X6: 150.2 | Y6: 157 | Z6: 163.6 | AA6: 155.2 | AB6: 157.2 | AC6: 156.7
A7: 44256 | B7: 64.729497 | C7: 142.5 | D7: 189.4 | E7: 163.2 | F7: 154.5 | G7: 168.2 | H7: 150.5 | I7: 141 | J7: 159.2 | K7: 111.7 | L7: 164 | M7: 160.6 | N7: 166.4 | O7: 154.5 | P7: 186.1 | Q7: 159.6 | R7: 154.4 | S7: 158.9 | T7: - | U7: 156 | V7: 154.8 | W7: 164.6 | X7: 151.3 | Y7: 157.8 | Z7: 163.8 | AA7: 153.1 | AB7: 157.3 | AC7: 156.7
A8: 44287 | B8: 63.396977 | C8: 142.7 | D8: 195.5 | E8: 163.4 | F8: 155 | G8: 175.2 | H8: 160.6 | I8: 135.1 | J8: 161.1 | K8: 112.2 | L8: 164.4 | M8: 161.9 | N8: 166.8 | O8: 155.6 | P8: 186.8 | Q8: 160.7 | R8: 155.1 | S8: 159.9 | T8: - | U8: 156 | V8: 155.5 | W8: 165.3 | X8: 151.7 | Y8: 158.6 | Z8: 164.1 | AA8: 154.6 | AB8: 158 | AC8: 157.6
A9: 44317 | B9: 66.953085 | C9: 145.1 | D9: 198.5 | E9: 168.6 | F9: 155.8 | G9: 184.4 | H9: 162.3 | I9: 138.4 | J9: 165.1 | K9: 114.3 | L9: 169.7 | M9: 164.6 | N9: 169.8 | O9: 158.7 | P9: 189.6 | Q9: 165.3 | R9: 160.6 | S9: 164.5 | T9: NA | U9: 161.7 | V9: 158.8 | W9: 169.1 | X9: 153.2 | Y9: 160 | Z9: 167.6 | AA9: 159.3 | AB9: 161.1 | AC9: 161.1
A10: 44348 | B10: 71.982647 | C10: 145.6 | D10: 200.1 | E10: 179.3 | F10: 156.1 | G10: 190.4 | H10: 158.6 | I10: 144.7 | J10: 165.5 | K10: 114.6 | L10: 170 | M10: 165.5 | N10: 171.7 | O10: 160.5 | P10: 189.1 | Q10: 165.3 | R10: 159.9 | S10: 164.6 | T10: NA | U10: 162.1 | V10: 159.2 | W10: 169.7 | X10: 154.2 | Y10: 160.4 | Z10: 166.8 | AA10: 159.4 | AB10: 161.5 | AC10: 162.1
A11: 44378 | B11: 73.539061 | C11: 145.1 | D11: 204.5 | E11: 180.4 | F11: 157.1 | G11: 188.7 | H11: 157.7 | I11: 152.8 | J11: 163.6 | K11: 113.9 | L11: 169.7 | M11: 166.2 | N11: 171 | O11: 161.7 | P11: 189.7 | Q11: 166 | R11: 161.1 | S11: 165.3 | T11: NA | U11: 162.5 | V11: 160.3 | W11: 170.4 | X11: 157.1 | Y11: 160.7 | Z11: 167.2 | AA11: 160.4 | AB11: 162.8 | AC11: 163.2
A12: 44409 | B12: 69.804724 | C12: 144.9 | D12: 202.3 | E12: 176.5 | F12: 157.5 | G12: 190.9 | H12: 155.7 | I12: 153.9 | J12: 162.8 | K12: 115.2 | L12: 169.8 | M12: 167.6 | N12: 171.9 | O12: 161.8 | P12: 190.2 | Q12: 167 | R12: 162.6 | S12: 166.3 | T12: NA | U12: 163.1 | V12: 160.9 | W12: 171.1 | X12: 157.7 | Y12: 161.1 | Z12: 167.5 | AA12: 160.3 | AB12: 163.3 | AC12: 163.6
A13: 44440 | B13: 73.130738 | C13: 145.4 | D13: 202.1 | E13: 172 | F13: 158 | G13: 195.5 | H13: 152.7 | I13: 151.4 | J13: 163.9 | K13: 119.3 | L13: 170.1 | M13: 168.3 | N13: 172.8 | O13: 162.1 | P13: 190.5 | Q13: 167.7 | R13: 163.6 | S13: 167.1 | T13: NA | U13: 163.7 | V13: 161.3 | W13: 171.9 | X13: 157.8 | Y13: 162.7 | Z13: 168.5 | AA13: 160.2 | AB13: 163.8 | AC13: 164
A14: 44470 | B14: 82.107394 | C14: 146.1 | D14: 202.5 | E14: 170.1 | F14: 158.4 | G14: 198.8 | H14: 152.6 | I14: 170.4 | J14: 165.2 | K14: 121.6 | L14: 170.6 | M14: 168.8 | N14: 173.6 | O14: 165.5 | P14: 191.2 | Q14: 168.9 | R14: 164.8 | S14: 168.3 | T14: NA | U14: 165.5 | V14: 162 | W14: 172.5 | X14: 159.5 | Y14: 163.2 | Z14: 169 | AA14: 161.1 | AB14: 164.7 | AC14: 166.3
A15: 44501 | B15: 80.637301 | C15: 146.9 | D15: 199.8 | E15: 171.5 | F15: 159.1 | G15: 198.4 | H15: 153.2 | I15: 183.9 | J15: 165.4 | K15: 122.1 | L15: 170.8 | M15: 169.1 | N15: 174.3 | O15: 167.5 | P15: 191.4 | Q15: 170.4 | R15: 166 | S15: 169.8 | T15: NA | U15: 165.3 | V15: 162.9 | W15: 173.4 | X15: 158.9 | Y15: 163.8 | Z15: 169.3 | AA15: 162.4 | AB15: 165.2 | AC15: 167.6
A16: 44531 | B16: 73.298824 | C16: 147.4 | D16: 197 | E16: 176.5 | F16: 159.8 | G16: 195.8 | H16: 152 | I16: 172.3 | J16: 164.5 | K16: 120.6 | L16: 171.7 | M16: 169.7 | N16: 175.1 | O16: 165.8 | P16: 190.8 | Q16: 171.8 | R16: 167.3 | S16: 171.2 | T16: NA | U16: 165.6 | V16: 163.9 | W16: 174 | X16: 160.1 | Y16: 164.5 | Z16: 169.7 | AA16: 162.8 | AB16: 166 | AC16: 167
... A28: 44896 | B28: 78.100942 | C28: 168.8 | D28: 206.9 | E28: 189.1 | F28: 173.4 | G28: 193.9 | H28: 156.7 | I28: 150.2 | J28: 170.5 | K28: 121.2 | L28: 207.5 | M28: 176.8 | N28: 187.7 | O28: 174.4 | P28: 195.9 | Q28: 188.1 | R28: 185.9 | S28: 187.8 | T28: NA | U28: 182.8 | V28: 176.4 | W28: 183.5 | X28: 167.8 | Y28: 171.2 | Z28: 177.3 | AA28: 175.7 | AB28: 175.5 | AC28: 177.1
A31: Urban CPI Inflation | C31: Correlation
C32: =CORREL($B$34:$B$57,C34:C57) -> 0.51787557 | D32: =CORREL($B$34:$B$57,D34:D57) -> 0.85586992 | E32: =CORREL($B$34:$B$57,E34:E57) -> -0.24788711 | F32: =CORREL($B$34:$B$57,F34:F57) -> 0.63625804 | G32: =CORREL($B$34:$B$57,G34:G57) -> 0.83897304 | H32: =CORREL($B$34:$B$57,H34:H57) -> 0.50631936 | I32: =CORREL($B$34:$B$57,I34:I57) -> 0.44664635 | J32: =CORREL($B$34:$B$57,J34:J57) -> 0.18641082 | ... AC32: =CORREL($B$34:$B$57,AC34:AC57) -> 0.75395554
A33: Date | B33: Oil Prices | C33: Cereals and products | D33: Meat and fish | E33: Egg | F33: Milk and products | G33: Oils and fats | H33: Fruits | I33: Vegetables | J33: Pulses and products | K33: Sugar and Confectionery | L33: Spices | M33: Non-alcoholic beverages | N33: Prepared meals, snacks, sweets etc. | O33: Food and beverages | P33: Pan, tobacco and intoxicants | Q33: Clothing | R33: Footwear | S33: Clothing and footwear | T33: Housing | U33: Fuel and light | V33: Household goods and services | W33: Health | X33: Transport and communication | Y33: Recreation and amusement | Z33: Education | AA33: Personal care and effects | AB33: Miscellaneous | AC33: General index
A34: 44197 | B34: 54.79457 | C34: 148 | D34: 194.8 | E34: 178.4 | F34: 154.4 | G34: 144.1 | H34: 152.6 | I34: 206.8 | J34: 162.1 | K34: 116.3 | L34: 163 | M34: 145.9 | N34: 167.2 | O34: 163.4 | P34: 191.8 | Q34: 152.5 | R34: 137.3 | S34: 150.2 | T34: 157.7 | U34: 142.9 | V34: 145.7 | W34: 154.1 | X34: 136.9 | Y34: 145.4 | Z34: 156.1 | AA34: 157.7 | AB34: 147.6 | AC34: 156
A35: 44228 | B35: 61.216117 | C35: 147.6 | D35: 191.2 | E35: 169.9 | F35: 155.1 | G35: 151.4 | H35: 154 | I35: 180.2 | J35: 159.8 | K35: 114.9 | L35: 162.5 | M35: 149.2 | N35: 169.4 | O35: 160.8 | P35: 193.3 | Q35: 154.2 | R35: 138.2 | S35: 151.8 | T35: 159.8 | U35: 149.1 | V35: 146.5 | W35: 156.3 | X35: 140.5 | Y35: 147.3 | Z35: 156.6 | AA35: 156.7 | AB35: 149.3 | AC35: 156.5
A36: 44256 | B36: 64.729497 | C36: 147.5 | D36: 197.5 | E36: 164.7 | F36: 155.6 | G36: 156.4 | H36: 157.3 | I36: 166.1 | J36: 161.1 | K36: 114.3 | L36: 162.6 | M36: 150.7 | N36: 170.3 | O36: 160.4 | P36: 193.5 | Q36: 155.1 | R36: 138.7 | S36: 152.6 | T36: 159.9 | U36: 154.8 | V36: 147.2 | W36: 156.9 | X36: 141.7 | Y36: 148.6 | Z36: 157.6 | AA36: 154.9 | AB36: 150 | AC36: 156.9
A37: 44287 | B37: 63.396977 | C37: 147.6 | D37: 202.5 | E37: 166.4 | F37: 156 | G37: 161.4 | H37: 168.8 | I37: 161.6 | J37: 162.8 | K37: 114.8 | L37: 162.8 | M37: 151.5 | N37: 171.4 | O37: 162 | P37: 194.4 | Q37: 155.9 | R37: 139.3 | S37: 153.4 | T37: 161.4 | U37: 154.9 | V37: 147.6 | W37: 157.5 | X37: 142.1 | Y37: 149.1 | Z37: 157.6 | AA37: 156.6 | AB37: 150.5 | AC37: 158
A38: 44317 | B38: 66.953085 | C38: 148.8 | D38: 204.3 | E38: 173 | F38: 156.5 | G38: 168.8 | H38: 172.5 | I38: 166.5 | J38: 165.9 | K38: 115.9 | L38: 165.2 | M38: 152 | N38: 171.1 | O38: 164.2 | P38: 198.2 | Q38: 156.5 | R38: 140.2 | S38: 154.1 | T38: 161.6 | U38: 155.5 | V38: 150.1 | W38: 160.4 | X38: 145 | Y38: 152.6 | Z38: 156.6 | AA38: 157.5 | AB38: 152.3 | AC38: 159.5
A39: 44348 | B39: 71.982647 | C39: 149.2 | D39: 205.5 | E39: 182.8 | F39: 156.5 | G39: 172.2 | H39: 171.5 | I39: 176.2 | J39: 166.9 | K39: 116.1 | L39: 165.5 | M39: 152.3 | N39: 173.3 | O39: 166.2 | P39: 195.6 | Q39: 157.3 | R39: 140.5 | S39: 154.8 | T39: 160.5 | U39: 156.1 | V39: 149.8 | W39: 160.8 | X39: 147.5 | Y39: 150.7 | Z39: 158.1 | AA39: 158 | AB39: 153.4 | AC39: 160.4
A40: 44378 | B40: 73.539061 | C40: 149.1 | D40: 210.9 | E40: 185 | F40: 158.2 | G40: 170.6 | H40: 170.9 | I40: 186.4 | J40: 164.7 | K40: 115.7 | L40: 165.5 | M40: 153.4 | N40: 173.5 | O40: 167.9 | P40: 195.5 | Q40: 157.9 | R40: 141.9 | S40: 155.5 | T40: 161.5 | U40: 157.7 | V40: 150.7 | W40: 161.5 | X40: 149.5 | Y40: 151.2 | Z40: 160.3 | AA40: 159.6 | AB40: 155 | AC40: 161.8
A41: 44409 | B41: 69.804724 | C41: 149.3 | D41: 207.4 | E41: 174.1 | F41: 159.2 | G41: 175 | H41: 161.3 | I41: 183.3 | J41: 164.5 | K41: 120.4 | L41: 166.2 | M41: 154.8 | N41: 175.1 | O41: 167.3 | P41: 196.5 | Q41: 159.8 | R41: 143.6 | S41: 157.3 | T41: 162.1 | U41: 160.7 | V41: 153.2 | W41: 162.8 | X41: 150.4 | Y41: 153.7 | Z41: 160.4 | AA41: 159.6 | AB41: 156 | AC41: 162.3
A42: 44440 | B42: 73.130738 | C42: 149.3 | D42: 207.4 | E42: 174.1 | F42: 159.1 | G42: 175 | H42: 161.2 | I42: 183.5 | J42: 164.5 | K42: 120.4 | L42: 166.2 | M42: 154.8 | N42: 175.1 | O42: 167.3 | P42: 196.5 | Q42: 159.8 | R42: 143.6 | S42: 157.4 | T42: 162.1 | U42: 160.8 | V42: 153.3 | W42: 162.8 | X42: 150.5 | Y42: 153.9 | Z42: 160.3 | AA42: 159.6 | AB42: 156 | AC42: 162.3
A43: 44470 | B43: 82.107394 | C43: 150.1 | D43: 208.4 | E43: 173 | F43: 159.2 | G43: 176.6 | H43: 159.3 | I43: 214.4 | J43: 165.3 | K43: 122.5 | L43: 166.8 | M43: 155.4 | N43: 175.9 | O43: 171.5 | P43: 197 | Q43: 160.8 | R43: 144.4 | S43: 158.3 | T43: 163.6 | U43: 162.2 | V43: 154.3 | W43: 163.5 | X43: 152.2 | Y43: 155.1 | Z43: 160.3 | AA43: 160.3 | AB43: 157 | AC43: 164.6
A44: 44501 | B44: 80.637301 | C44: 151 | D44: 204.9 | E44: 175.4 | F44: 159.6 | G44: 175.8 | H44: 160.3 | I44: 229.1 | J44: 165.1 | K44: 123.1 | L44: 167.2 | M44: 156.1 | N44: 176.8 | O44: 173.5 | P44: 197 | Q44: 162.3 | R44: 145.3 | S44: 159.7 | T44: 164.2 | U44: 161.6 | V44: 155.2 | W44: 164.2 | X44: 151.2 | Y44: 156.7 | Z44: 160.8 | AA44: 161.8 | AB44: 157.3 | AC44: 165.6
A45: 44531 | B45: 73.298824 | C45: 151.6 | D45: 202.2 | E45: 180 | F45: 160 | G45: 173.5 | H45: 158.3 | I45: 219.5 | J45: 164.2 | K45: 121.9 | L45: 168.2 | M45: 156.5 | N45: 178.2 | O45: 172.2 | P45: 196.8 | Q45: 163.3 | R45: 146.7 | S45: 160.7 | T45: 163.4 | U45: 161.7 | V45: 156 | W45: 165.1 | X45: 151.8 | Y45: 157.6 | Z45: 160.6 | AA45: 162.4 | AB45: 157.8 | AC45: 165.2
... A57: 44896 | B57: 78.100942 | C57: 170.2 | D57: 212.9 | E57: 191.9 | F57: 173.9 | G57: 179.1 | H57: 159.5 | I57: 178.7 | J57: 171.3 | K57: 123.1 | L57: 200.5 | M57: 162.8 | N57: 193.3 | O57: 178.6 | P57: 201.1 | Q57: 177.7 | R57: 164.5 | S57: 175.7 | T57: 170.7 | U57: 180.6 | V57: 167.3 | W57: 177.2 | X57: 159.4 | Y57: 167.1 | Z57: 171.8 | AA57: 176 | AB57: 168.2 | AC57: 174.1
A61: Urban+Rural CPI Inflation | C61: Correlation
C62: =CORREL($B$64:$B$87,C64:C87) -> 0.50782674 | D62: =CORREL($B$64:$B$87,D64:D87) -> 0.84191192 | E62: =CORREL($B$64:$B$87,E64:E87) -> -0.20362247 | F62: =CORREL($B$64:$B$87,F64:F87) -> 0.63436439 | G62: =CORREL($B$64:$B$87,G64:G87) -> 0.82620259 | H62: =CORREL($B$64:$B$87,H64:H87) -> 0.59139323 | I62: =CORREL($B$64:$B$87,I64:I87) -> 0.35074653 | J62: =CORREL($B$64:$B$87,J64:J87) -> 0.36427004 | ... AC62: =CORREL($B$64:$B$87,AC64:AC87) -> 0.74098995
A63: Date | B63: Oil Prices | C63: Cereals and products | D63: Meat and fish | E63: Egg | F63: Milk and products | G63: Oils and fats | H63: Fruits | I63: Vegetables | J63: Pulses and products | K63: Sugar and Confectionery | L63: Spices | M63: Non-alcoholic beverages | N63: Prepared meals, snacks, sweets etc. | O63: Food and beverages | P63: Pan, tobacco and intoxicants | Q63: Clothing | R63: Footwear | S63: Clothing and footwear | T63: Housing | U63: Fuel and light | V63: Household goods and services | W63: Health | X63: Transport and communication | Y63: Recreation and amusement | Z63: Education | AA63: Personal care and effects | AB63: Miscellaneous | AC63: General index
A64: 44197 | B64: 54.79457 | C64: 144.9 | D64: 190.1 | E64: 175.3 | F64: 154.1 | G64: 150.9 | H64: 149.6 | I64: 194.2 | J64: 160.4 | K64: 114.6 | L64: 164 | M64: 151.8 | N64: 165.6 | O64: 161 | P64: 186.5 | Q64: 155.5 | R64: 146.1 | S64: 154.2 | T64: 157.7 | U64: 147.9 | V64: 150 | W64: 159.3 | X64: 141.9 | Y64: 149.6 | Z64: 159.2 | AA64: 156.8 | AB64: 151.9 | AC64: 157.3
A65: 44228 | B65: 61.216117 | C65: 144.3 | D65: 186.5 | E65: 168.7 | F65: 154.7 | G65: 158.7 | H65: 150.7 | I65: 160 | J65: 158.8 | K65: 112.8 | L65: 164.2 | M65: 155.5 | N65: 167.5 | O65: 156.9 | P65: 188.3 | Q65: 157.2 | R65: 147.4 | S65: 155.8 | T65: 159.8 | U65: 152.4 | V65: 150.9 | W65: 161.3 | X65: 145.1 | Y65: 151.5 | Z65: 159.5 | AA65: 155.8 | AB65: 153.4 | AC65: 156.6
A66: 44256 | B66: 64.729497 | C66: 144.1 | D66: 192.2 | E66: 163.8 | F66: 154.9 | G66: 163.9 | H66: 153.7 | I66: 149.5 | J66: 159.8 | K66: 112.6 | L66: 163.5 | M66: 156.5 | N66: 168.2 | O66: 156.7 | P66: 188.1 | Q66: 157.8 | R66: 147.9 | S66: 156.4 | T66: 159.9 | U66: 155.5 | V66: 151.2 | W66: 161.7 | X66: 146.2 | Y66: 152.6 | Z66: 160.2 | AA66: 153.8 | AB66: 153.8 | AC66: 156.8
A67: 44287 | B67: 63.396977 | C67: 144.3 | D67: 198 | E67: 164.6 | F67: 155.4 | G67: 170.1 | H67: 164.4 | I67: 144.1 | J67: 161.7 | K67: 113.1 | L67: 163.9 | M67: 157.6 | N67: 168.9 | O67: 158 | P67: 188.8 | Q67: 158.8 | R67: 148.5 | S67: 157.3 | T67: 161.4 | U67: 155.6 | V67: 151.8 | W67: 162.3 | X67: 146.6 | Y67: 153.2 | Z67: 160.3 | AA67: 155.4 | AB67: 154.4 | AC67: 157.8
A68: 44317 | B68: 66.953085 | C68: 146.3 | D68: 200.5 | E68: 170.3 | F68: 156.1 | G68: 178.7 | H68: 167.1 | I68: 147.9 | J68: 165.4 | K68: 114.8 | L68: 168.2 | M68: 159.3 | N68: 170.4 | O68: 160.7 | P68: 191.9 | Q68: 161.8 | R68: 152.1 | S68: 160.4 | T68: 161.6 | U68: 159.4 | V68: 154.7 | W68: 165.8 | X68: 148.9 | Y68: 155.8 | Z68: 161.2 | AA68: 158.6 | AB68: 156.8 | AC68: 160.4
A69: 44348 | B69: 71.982647 | C69: 146.7 | D69: 202 | E69: 180.7 | F69: 156.2 | G69: 183.7 | H69: 164.6 | I69: 155.4 | J69: 166 | K69: 115.1 | L69: 168.5 | M69: 160 | N69: 172.4 | O69: 162.6 | P69: 190.8 | Q69: 162.2 | R69: 151.8 | S69: 160.7 | T69: 160.5 | U69: 159.8 | V69: 154.8 | W69: 166.3 | X69: 150.7 | Y69: 154.9 | Z69: 161.7 | AA69: 158.8 | AB69: 157.6 | AC69: 161.3
A70: 44378 | B70: 73.539061 | C70: 146.4 | D70: 206.8 | E70: 182.2 | F70: 157.5 | G70: 182.1 | H70: 163.9 | I70: 164.2 | J70: 164 | K70: 114.5 | L70: 168.3 | M70: 160.9 | N70: 172.2 | O70: 164 | P70: 191.2 | Q70: 162.8 | R70: 153.1 | S70: 161.4 | T70: 161.5 | U70: 160.7 | V70: 155.8 | W70: 167 | X70: 153.1 | Y70: 155.3 | Z70: 163.2 | AA70: 160.1 | AB70: 159 | AC70: 162.5
A71: 44409 | B71: 69.804724 | C71: 146.6 | D71: 204 | E71: 172.8 | F71: 158.4 | G71: 188 | H71: 156.8 | I71: 162.2 | J71: 164.1 | K71: 119.7 | L71: 168.8 | M71: 162.7 | N71: 173.9 | O71: 164 | P71: 192.1 | Q71: 164.5 | R71: 155.3 | S71: 163.2 | T71: 162.1 | U71: 162.6 | V71: 157.5 | W71: 168.4 | X71: 154 | Y71: 157.6 | Z71: 163.8 | AA71: 160 | AB71: 160 | AC71: 163.2
A72: 44440 | B72: 73.130738 | C72: 146.6 | D72: 204 | E72: 172.8 | F72: 158.4 | G72: 188 | H72: 156.7 | I72: 162.3 | J72: 164.1 | K72: 119.7 | L72: 168.8 | M72: 162.7 | N72: 173.9 | O72: 164 | P72: 192.1 | Q72: 164.6 | R72: 155.3 | S72: 163.3 | T72: 162.1 | U72: 162.6 | V72: 157.5 | W72: 168.4 | X72: 154 | Y72: 157.7 | Z72: 163.7 | AA72: 160 | AB72: 160 | AC72: 163.2
A73: 44470 | B73: 82.107394 | C73: 147.4 | D73: 204.6 | E73: 171.2 | F73: 158.7 | G73: 190.6 | H73: 155.7 | I73: 185.3 | J73: 165.2 | K73: 121.9 | L73: 169.3 | M73: 163.2 | N73: 174.7 | O73: 167.7 | P73: 192.7 | Q73: 165.7 | R73: 156.3 | S73: 164.3 | T73: 163.6 | U73: 164.2 | V73: 158.4 | W73: 169.1 | X73: 155.7 | Y73: 158.6 | Z73: 163.9 | AA73: 160.8 | AB73: 161 | AC73: 165.5
A74: 44501 | B74: 80.637301 | C74: 148.2 | D74: 201.6 | E74: 173 | F74: 159.3 | G74: 190.1 | H74: 156.5 | I74: 199.2 | J74: 165.3 | K74: 122.4 | L74: 169.6 | M74: 163.7 | N74: 175.5 | O74: 169.7 | P74: 192.9 | Q74: 167.2 | R74: 157.4 | S74: 165.8 | T74: 164.2 | U74: 163.9 | V74: 159.3 | W74: 169.9 | X74: 154.8 | Y74: 159.8 | Z74: 164.3 | AA74: 162.2 | AB74: 161.4 | AC74: 166.7
A75: 44531 | B75: 73.298824 | C75: 148.7 | D75: 198.8 | E75: 177.9 | F75: 159.9 | G75: 187.6 | H75: 154.9 | I75: 188.3 | J75: 164.4 | K75: 121 | L75: 170.5 | M75: 164.2 | N75: 176.5 | O75: 168.2 | P75: 192.4 | Q75: 168.5 | R75: 158.7 | S75: 167 | T75: 163.4 | U75: 164.1 | V75: 160.2 | W75: 170.6 | X75: 155.7 | Y75: 160.6 | Z75: 164.4 | AA75: 162.6 | AB75: 162 | AC75: 166.2
... A87: 44896 | B87: 78.100942 | C87: 169.2 | D87: 209 | E87: 190.2 | F87: 173.6 | G87: 188.5 | H87: 158 | I87: 159.9 | J87: 170.8 | K87: 121.8 | L87: 205.2 | M87: 171 | N87: 190.3 | O87: 175.9 | P87: 197.3 | Q87: 184 | R87: 177 | S87: 183 | T87: 170.7 | U87: 182 | V87: 172.1 | W87: 181.1 | X87: 163.4 | Y87: 168.9 | Z87: 174.1 | AA87: 175.8 | AB87: 172 | AC87: 175.7
A89: We have colored the Increased inflation of a price category in RED.
A90: We have colored the decreased inflation of a price category in GREEN.
